Workbook

Sheet Guide
A1: VIXIV LTD — Generic flip programme (deal secured → sale completed)
A3: HOW TO USE
A4: 1. Open a Deal tab. Fill the yellow cells: deal name, route (Auction / Estate agent), deal secured date, contractor.
A5: 2. Set the scope switches (Y/N). Activities switched off grey out and take no time; their successors close up automatically.
A6: 3. Replace the default durations (yellow, working days) with your builder's programme once you have it.
A7: 4. Read the Flags column and Key Dates. Hold points (yellow rows) are go/no-go decisions — do not pass them without a decision.
A8: 5. The Pipeline tab compares Deal 1 and Deal 2 and flags if both builds need the crew at the same time.
A9: 6. Update Status as work progresses. To start a new deal, copy a Deal tab (right-click → Move or Copy → Create a copy).
A11: SCHEDULING LOGIC
A12: • All durations are WORKING days (Mon–Fri) and skip every date on the Holidays tab.
A13: • FS = finish-to-start: starts the working day after the predecessor finishes, plus any lag.
A14: • SS = start-to-start: starts with the predecessor, plus the lag in working days.
... A27: Yellow cell + blue text = input you edit. Black = formula. Green text = link from another tab. Red text = flag.

Sheet Pipeline
A1: Pipeline — two overlapping flips
A2: Pulls key dates from Deal 1 and Deal 2. The crew check flags if both builds run at once. To add Deal 3: copy a deal tab and add a column here.
B4: Deal 1 | C4: Deal 2
A5: Deal | B5: ='Deal 1'!$C$5 -> EXAMPLE — 2-bed terrace, Rochdale (replace) | C5: ='Deal 2'!$C$5 -> EXAMPLE — 3-bed semi via agent (replace)
A6: Route | B6: ='Deal 1'!$C$6 -> Auction | C6: ='Deal 2'!$C$6 -> Estate agent
A7: Lead contractor | B7: ='Deal 1'!$C$14 -> Mentor's crew (TBC) | C7: ='Deal 2'!$C$14 -> Friend (general builder)
A8: Deal secured | B8: ='Deal 1'!$C$7 -> 46366 | C8: ='Deal 2'!$C$7 -> 46419
A9: Purchase completion | B9: ='Deal 1'!$I$5 -> 46394 | C9: ='Deal 2'!$I$5 -> 46477
A10: Works start | B10: ='Deal 1'!$I$6 -> 46402 | C10: ='Deal 2'!$I$6 -> 46485
A11: Practical completion | B11: ='Deal 1'!$I$7 -> 46485 | C11: ='Deal 2'!$I$7 -> 46563
A12: Listed | B12: ='Deal 1'!$I$8 -> 46490 | C12: ='Deal 2'!$I$8 -> 46568
A13: Sale completed | B13: ='Deal 1'!$I$10 -> 46605 | C13: ='Deal 2'!$I$10 -> 46682
A14: Months owned | B14: ='Deal 1'!$I$12 -> 6.9316689 | C14: ='Deal 2'!$I$12 -> 6.7345598
A15: Bridge headroom (months) | B15: ='Deal 1'!$I$13 -> 5.0683311 | C15: ='Deal 2'!$I$13 -> 5.2654402
A17: Crew clash check | B17: =IF(AND(B10<C11,C10<B11),"⚠ Builds overlap by "&(MIN(B11,C11)-MAX(B10,C10))&" day(s): confirm a second crew or move Deal 2 later","✓ No build overlap: one crew can run both back-to-back") -> ✓ No build overlap: one crew can run both back-to-back
A18: Capital overlap (both owned at once, days) | B18: =MAX(0,MIN(B13,C13)-MAX(B8,C8)) -> 186 | C18: Days both purchases are funded at the same time — check against the £50k pool.
A21: Phase timeline (weekly) | D21: =TEXT(D22,"mmm yy") -> Dec 26 | E21: =IF(MONTH(E22)<>MONTH(D22),TEXT(E22,"mmm yy"),"") | F21: =IF(MONTH(F22)<>MONTH(E22),TEXT(F22,"mmm yy"),"") | G21: =IF(MONTH(G22)<>MONTH(F22),TEXT(G22,"mmm yy"),"") | H21: =IF(MONTH(H22)<>MONTH(G22),TEXT(H22,"mmm yy"),"") -> Jan 27 | I21: =IF(MONTH(I22)<>MONTH(H22),TEXT(I22,"mmm yy"),"") | J21: =IF(MONTH(J22)<>MONTH(I22),TEXT(J22,"mmm yy"),"") | K21: =IF(MONTH(K22)<>MONTH(J22),TEXT(K22,"mmm yy"),"") | L21: =IF(MONTH(L22)<>MONTH(K22),TEXT(L22,"mmm yy"),"") -> Feb 27 | ... CC21: =IF(MONTH(CC22)<>MONTH(CB22),TEXT(CC22,"mmm yy"),"")
B22: Start | C22: End | D22: =MIN(B8,C8)-WEEKDAY(MIN(B8,C8),3) -> 46363 | E22: =D22+7 -> 46370 | F22: =E22+7 -> 46377 | G22: =F22+7 -> 46384 | H22: =G22+7 -> 46391 | I22: =H22+7 -> 46398 | J22: =I22+7 -> 46405 | K22: =J22+7 -> 46412 | L22: =K22+7 -> 46419 | ... CC22: =CB22+7 -> 46902
A23: Deal 1 — Legal | B23: =B8 -> 46366 | C23: =B9 -> 46394
A24: Deal 1 — Build | B24: =B10 -> 46402 | C24: =B11 -> 46485
A25: Deal 1 — Sale | B25: =B12 -> 46490 | C25: =B13 -> 46605
A26: Deal 2 — Legal | B26: =C8 -> 46419 | C26: =C9 -> 46477
A27: Deal 2 — Build | B27: =C10 -> 46485 | C27: =C11 -> 46563
A28: Deal 2 — Sale | B28: =C12 -> 46568 | C28: =C13 -> 46682

Sheet DD Checklist
A1: Default due-diligence checklist
A2: Stage 1 is done BEFORE bidding (auction) or before the offer is final (agent). Programme ID links each later check to its activity.
A4: # | B4: Stage | C4: Check | D4: Why it matters / what good looks like | E4: Programme ID | F4: Done (Y/N) | G4: Notes
A5: 1 | B5: 1 Before bid / offer | C5: Read the full legal pack with your solicitor | D5: Title, searches, special conditions, completion period, extra fees the buyer pays. | E5: A7
A6: 2 | B6: 1 Before bid / offer | C6: Check special conditions for hidden costs | D6: Seller's legal fees, search fees, arrears, VAT — add all to the appraisal. | E6: —
A7: 3 | B7: 1 Before bid / offer | C7: Why is it at auction / why is it cheap? | D7: Unmortgageable, probate, repossession, structural defect, short lease, sitting tenant. | E7: —
A8: 4 | B8: 1 Before bid / offer | C8: View with the builder; photos and video | D8: Builder's schedule of works and price range before you bid. | E8: B1
A9: 5 | B9: 1 Before bid / offer | C9: Three or more sold comparables (same street/type, last 12 months) | D9: Set the WORST-CASE end value (training rule). | E9: —
A10: 6 | B10: 1 Before bid / offer | C10: DealsDash appraisal: max bid incl. SDLT, fees, buyer's premium | D10: Profit first; stress tests and walk-away tests pass. | E10: —
A11: 7 | B11: 1 Before bid / offer | C11: Construction type and end-buyer mortgageability | D11: Non-standard construction or defects can kill the resale. Your buyer needs a mortgage. | E11: —
A12: 8 | B12: 1 Before bid / offer | C12: Mining, flood, knotweed, conservation area, planning history | D12: Rochdale is a former coalfield: check the Coal Authority report. | E12: —
A13: 9 | B13: 1 Before bid / offer | C13: Tenure and occupancy | D13: Freehold vs leasehold terms; vacant possession confirmed. | E13: —
A14: 10 | B14: 1 Before bid / offer | C14: Bridging decision in principle; lender can complete within 28 days | D14: No DIP = no bid. | E14: A5
A15: 11 | B15: 1 Before bid / offer | C15: Deposit (10%) + fees available on the day; insurance quote ready | D15: Bind insurance at the hammer. | E15: A2
A16: 12 | B16: 1 Before bid / offer | C16: Set the absolute maximum bid and walk away above it | D16: Write it down before the auction starts. | E16: —
... A19: 15 | B19: 2 After deal secured | C19: Contractor contract signed; insurance seen; CIS verified | D19: Fixed price by stage, 5% retention. | E19: B3
A20: 16 | B20: 2 After deal secured | C20: Asbestos survey (pre-2000) before strip-out | E20: B6
A21: 17 | B21: 3 During works | C21: Opening-up review: costs updated in DealsDash | D21: Hidden defects found here; re-check profit. | E21: C2
A22: 18 | B22: 3 During works | C22: First-fix photos before boarding | D22: Proof for certificates and future buyers. | E22: D4
A23: 19 | B23: 4 Before listing | C23: All certificates collected (EIC, Gas Safe, FENSA, Building Control, damp guarantee) | D23: Buyer's solicitor will ask. | E23: G1
A24: 20 | B24: 4 Before listing | C24: EPC commissioned | D24: Must be commissioned before marketing. | E24: G4
A25: 21 | B25: 4 Before listing | C25: Three agent valuations vs your worst-case end value | D25: Price realistically from day one. | E25: H1
A26: 22 | B26: 5 Sale | C26: Sale progression chased weekly | D26: Most delays are paperwork. | E26: H5
A27: 23 | B27: 5 Sale | C27: Bridge redemption statement requested two weeks before completion | D27: No surprise interest or fees. | E27: H7
A28: 24 | B28: 5 Sale | C28: Close-out: actual vs appraised profit and durations | D28: Update this template's default durations. | E28: H9

Sheet Deal 1
A1: VIXIV LTD — Flip programme: Deal 1
A2: Edit only the YELLOW cells (blue text). Dates, Gantt and flags recalculate. Durations are working days. Example values shown — replace with your deal.
B4: DEAL INPUTS | E4: SCOPE SWITCHES (Y/N) | H4: KEY DATES (calculated)
B5: Deal name / address | C5: EXAMPLE — 2-bed terrace, Rochdale (replace) | E5: Pre-2000 build | F5: Y | H5: Purchase completion | I5: =$P$32 -> 46394
B6: Purchase route | C6: Auction | E6: Structural | F6: N | H6: Works start (strip-out) | I6: =$O$40 -> 46402
B7: Deal secured date | C7: 46366 | E7: Damp/timber | F7: Y | H7: Practical completion | I7: =$O$63 -> 46485
B8: Auction completion period (calendar days) | C8: 28 | E8: Roof/external | F8: N | H8: Listed | I8: =$O$67 -> 46490
B9: Agent route: exchange → completion (WD) | C9: 10 | E9: Windows/doors | F9: N | H9: Sale agreed | I9: =$P$68 -> 46533
B10: Contingency on construction durations | C10: 0.15 | E10: Rewire | F10: Y | H10: Sale completed | I10: =$P$72 -> 46605
B11: Winter drying allowance (extra WD, Nov–Feb) | C11: 3 | E11: Heating/boiler | F11: Y | H11: Build duration (WD) | I11: =NETWORKDAYS($I$6,$I$7,Holidays!$B$5:$B$60) -> 58
B12: WD to agree a sale after listing | C12: 30 | E12: Kitchen | F12: Y | H12: Months owned (completion → sale) | I12: =($I$10-$I$5)/30.44 -> 6.9316689
B13: Bridge term (months) | C13: 12 | E13: Bathroom | F13: Y | H13: Bridge headroom (months) | I13: =$C$13-$I$12 -> 5.0683311
B14: Lead contractor | C14: Mentor's crew (TBC) | H14: Deal secured → sale completed (days) | I14: =$I$10-$C$7 -> 239
B15: Sale: exchange → completion (WD) | C15: 10
B17: Gantt key: | C17: A Purchase & DD | D17: B Pre-start | E17: C Strip-out & structure | F17: D First fix | G17: E Plaster | H17: F Second fix & finish | I17: G Sign-off | J17: H Sale & close-out | K17: ■ milestone
U19: =TEXT(U20,"mmm yy") -> Dec 26 | V19: =IF(MONTH(V20)<>MONTH(U20),TEXT(V20,"mmm yy"),"") | W19: =IF(MONTH(W20)<>MONTH(V20),TEXT(W20,"mmm yy"),"") | X19: =IF(MONTH(X20)<>MONTH(W20),TEXT(X20,"mmm yy"),"") | Y19: =IF(MONTH(Y20)<>MONTH(X20),TEXT(Y20,"mmm yy"),"") -> Jan 27 | Z19: =IF(MONTH(Z20)<>MONTH(Y20),TEXT(Z20,"mmm yy"),"") | AA19: =IF(MONTH(AA20)<>MONTH(Z20),TEXT(AA20,"mmm yy"),"") | AB19: =IF(MONTH(AB20)<>MONTH(AA20),TEXT(AB20,"mmm yy"),"") | AC19: =IF(MONTH(AC20)<>MONTH(AB20),TEXT(AC20,"mmm yy"),"") -> Feb 27 | ... CB19: =IF(MONTH(CB20)<>MONTH(CA20),TEXT(CB20,"mmm yy"),"")
A20: ID | B20: Phase | C20: Activity | D20: Owner | E20: Route | F20: Scope switch | G20: Hold point | H20: Dur WD (auction) | I20: Dur WD (agent) | J20: Contingency? | K20: Applies? | L20: Dur used (WD) | M20: Predecessors | N20: Lag (WD) | O20: Start | P20: Finish | Q20: Status | R20: Flags | S20: Notes / what good looks like | U20: =$O$21-WEEKDAY($O$21,3) -> 46363 | V20: =U20+7 -> 46370 | W20: =V20+7 -> 46377 | X20: =W20+7 -> 46384 | Y20: =X20+7 -> 46391 | Z20: =Y20+7 -> 46398 | AA20: =Z20+7 -> 46405 | AB20: =AA20+7 -> 46412 | AC20: =AB20+7 -> 46419 | ... CB20: =CA20+7 -> 46776
A21: A1 | B21: A Purchase & DD | C21: Deal secured (auction: hammer falls = exchange; agent: offer accepted) | D21: Paul | E21: Both | H21: 0 | I21: 0 | J21: N | K21: =IF(AND(OR($E21="Both",$E21=$C$6),OR($F21="",IFERROR(INDEX($F$5:$F$13,MATCH($F21,$E$5:$E$13,0)),"Y")="Y")),"Y","N") -> Y | L21: =IF($K21="N",0,IF(IF($C$6="Auction",$H21,$I21)=0,0,ROUNDUP(IF($C$6="Auction",$H21,$I21)*(1+IF($J21="Y",$C$10,0)),0))) -> 0 | M21: — | N21: 0 | O21: =WORKDAY($C$7-1,1,Holidays!$B$5:$B$60) -> 46366 | P21: =IF($K21="N",WORKDAY($O21,-1,Holidays!$B$5:$B$60),IF($L21=0,$O21,WORKDAY($O21,$L21-1,Holidays!$B$5:$B$60))) -> 46366 | Q21: Not started | R21: =IF(AND($G21="HOLD",$K21="Y"),"■ HOLD: go/no-go. ","") | S21: Day 0. Everything else is driven from the date in C7.
A22: A2 | B22: A Purchase & DD | C22: Buildings insurance (unoccupied cover) in force | D22: Paul / broker | E22: Both | H22: 1 | I22: 1 | J22: N | K22: =IF(AND(OR($E22="Both",$E22=$C$6),OR($F22="",IFERROR(INDEX($F$5:$F$13,MATCH($F22,$E$5:$E$13,0)),"Y")="Y")),"Y","N") -> Y | L22: =IF($K22="N",0,IF(IF($C$6="Auction",$H22,$I22)=0,0,ROUNDUP(IF($C$6="Auction",$H22,$I22)*(1+IF($J22="Y",$C$10,0)),0))) -> 1 | M22: A1SS | N22: 0 | O22: =WORKDAY($O$21,$N22,Holidays!$B$5:$B$60) -> 46366 | P22: =IF($K22="N",WORKDAY($O22,-1,Holidays!$B$5:$B$60),IF($L22=0,$O22,WORKDAY($O22,$L22-1,Holidays!$B$5:$B$60))) -> 46366 | Q22: Not started | R22: =IF(AND($G22="HOLD",$K22="Y"),"■ HOLD: go/no-go. ","") | S22: Auction: risk passes to you at the hammer. Agent route: must be on cover from exchange at the latest.
A23: A3 | B23: A Purchase & DD | C23: Pay 10% deposit + buyer's premium / auction fees | D23: Paul | E23: Auction | H23: 1 | I23: 0 | J23: N | K23: =IF(AND(OR($E23="Both",$E23=$C$6),OR($F23="",IFERROR(INDEX($F$5:$F$13,MATCH($F23,$E$5:$E$13,0)),"Y")="Y")),"Y","N") -> Y | L23: =IF($K23="N",0,IF(IF($C$6="Auction",$H23,$I23)=0,0,ROUNDUP(IF($C$6="Auction",$H23,$I23)*(1+IF($J23="Y",$C$10,0)),0))) -> 1 | M23: A1SS | N23: 0 | O23: =WORKDAY($O$21,$N23,Holidays!$B$5:$B$60) -> 46366 | P23: =IF($K23="N",WORKDAY($O23,-1,Holidays!$B$5:$B$60),IF($L23=0,$O23,WORKDAY($O23,$L23-1,Holidays!$B$5:$B$60))) -> 46366 | Q23: Not started | R23: =IF(AND($G23="HOLD",$K23="Y"),"■ HOLD: go/no-go. ","") | S23: Paid on the day. Funds must be ready before you bid.
A24: A4 | B24: A Purchase & DD | C24: Instruct solicitor; legal pack / memorandum of sale to solicitor and lender | D24: Paul | E24: Both | H24: 2 | I24: 2 | J24: N | K24: =IF(AND(OR($E24="Both",$E24=$C$6),OR($F24="",IFERROR(INDEX($F$5:$F$13,MATCH($F24,$E$5:$E$13,0)),"Y")="Y")),"Y","N") -> Y | L24: =IF($K24="N",0,IF(IF($C$6="Auction",$H24,$I24)=0,0,ROUNDUP(IF($C$6="Auction",$H24,$I24)*(1+IF($J24="Y",$C$10,0)),0))) -> 2 | M24: A1SS | N24: 0 | O24: =WORKDAY($O$21,$N24,Holidays!$B$5:$B$60) -> 46366 | P24: =IF($K24="N",WORKDAY($O24,-1,Holidays!$B$5:$B$60),IF($L24=0,$O24,WORKDAY($O24,$L24-1,Holidays!$B$5:$B$60))) -> 46367 | Q24: Not started | R24: =IF(AND($G24="HOLD",$K24="Y"),"■ HOLD: go/no-go. ","")
A25: A5 | B25: A Purchase & DD | C25: Bridging valuation instructed and inspection done | D25: Broker / lender | E25: Both | H25: 5 | I25: 5 | J25: N | K25: =IF(AND(OR($E25="Both",$E25=$C$6),OR($F25="",IFERROR(INDEX($F$5:$F$13,MATCH($F25,$E$5:$E$13,0)),"Y")="Y")),"Y","N") -> Y | L25: =IF($K25="N",0,IF(IF($C$6="Auction",$H25,$I25)=0,0,ROUNDUP(IF($C$6="Auction",$H25,$I25)*(1+IF($J25="Y",$C$10,0)),0))) -> 5 | M25: A4SS | N25: 1 | O25: =WORKDAY($O$24,$N25,Holidays!$B$5:$B$60) -> 46367 | P25: =IF($K25="N",WORKDAY($O25,-1,Holidays!$B$5:$B$60),IF($L25=0,$O25,WORKDAY($O25,$L25-1,Holidays!$B$5:$B$60))) -> 46373 | Q25: Not started | R25: =IF(AND($G25="HOLD",$K25="Y"),"■ HOLD: go/no-go. ","") | S25: Ideally have a decision in principle BEFORE the auction.
A26: A6 | B26: A Purchase & DD | C26: Bridging underwriting and formal loan offer | D26: Lender | E26: Both | H26: 5 | I26: 5 | J26: N | K26: =IF(AND(OR($E26="Both",$E26=$C$6),OR($F26="",IFERROR(INDEX($F$5:$F$13,MATCH($F26,$E$5:$E$13,0)),"Y")="Y")),"Y","N") -> Y | L26: =IF($K26="N",0,IF(IF($C$6="Auction",$H26,$I26)=0,0,ROUNDUP(IF($C$6="Auction",$H26,$I26)*(1+IF($J26="Y",$C$10,0)),0))) -> 5 | M26: A5FS | N26: 0 | O26: =WORKDAY($P$25,1+$N26,Holidays!$B$5:$B$60) -> 46374 | P26: =IF($K26="N",WORKDAY($O26,-1,Holidays!$B$5:$B$60),IF($L26=0,$O26,WORKDAY($O26,$L26-1,Holidays!$B$5:$B$60))) -> 46380 | Q26: Not started | R26: =IF(AND($G26="HOLD",$K26="Y"),"■ HOLD: go/no-go. ","")
A27: A7 | B27: A Purchase & DD | C27: Searches and enquiries raised and answered | D27: Solicitor | E27: Estate agent | H27: 0 | I27: 25 | J27: N | K27: =IF(AND(OR($E27="Both",$E27=$C$6),OR($F27="",IFERROR(INDEX($F$5:$F$13,MATCH($F27,$E$5:$E$13,0)),"Y")="Y")),"Y","N") -> N | L27: =IF($K27="N",0,IF(IF($C$6="Auction",$H27,$I27)=0,0,ROUNDUP(IF($C$6="Auction",$H27,$I27)*(1+IF($J27="Y",$C$10,0)),0))) -> 0 | M27: A4FS | N27: 0 | O27: =WORKDAY($P$24,1+$N27,Holidays!$B$5:$B$60) -> 46370 | P27: =IF($K27="N",WORKDAY($O27,-1,Holidays!$B$5:$B$60),IF($L27=0,$O27,WORKDAY($O27,$L27-1,Holidays!$B$5:$B$60))) -> 46367 | Q27: Not started | R27: =IF(AND($G27="HOLD",$K27="Y"),"■ HOLD: go/no-go. ","") | S27: Auction route: done BEFORE bidding (see DD Checklist).
A28: A8 | B28: A Purchase & DD | C28: Independent survey + builder walk-round for quote | D28: Surveyor / builder | E28: Estate agent | H28: 0 | I28: 10 | J28: N | K28: =IF(AND(OR($E28="Both",$E28=$C$6),OR($F28="",IFERROR(INDEX($F$5:$F$13,MATCH($F28,$E$5:$E$13,0)),"Y")="Y")),"Y","N") -> N | L28: =IF($K28="N",0,IF(IF($C$6="Auction",$H28,$I28)=0,0,ROUNDUP(IF($C$6="Auction",$H28,$I28)*(1+IF($J28="Y",$C$10,0)),0))) -> 0 | M28: A4SS | N28: 2 | O28: =WORKDAY($O$24,$N28,Holidays!$B$5:$B$60) -> 46370 | P28: =IF($K28="N",WORKDAY($O28,-1,Holidays!$B$5:$B$60),IF($L28=0,$O28,WORKDAY($O28,$L28-1,Holidays!$B$5:$B$60))) -> 46367 | Q28: Not started | R28: =IF(AND($G28="HOLD",$K28="Y"),"■ HOLD: go/no-go. ","")
A29: A9 | B29: A Purchase & DD | C29: Review title, searches and survey: renegotiate or withdraw | D29: Paul + mentor | E29: Estate agent | G29: HOLD | H29: 0 | I29: 3 | J29: N | K29: =IF(AND(OR($E29="Both",$E29=$C$6),OR($F29="",IFERROR(INDEX($F$5:$F$13,MATCH($F29,$E$5:$E$13,0)),"Y")="Y")),"Y","N") -> N | L29: =IF($K29="N",0,IF(IF($C$6="Auction",$H29,$I29)=0,0,ROUNDUP(IF($C$6="Auction",$H29,$I29)*(1+IF($J29="Y",$C$10,0)),0))) -> 0 | M29: A7FS; A8FS | N29: 0 | O29: =MAX(WORKDAY($P$27,1+$N29,Holidays!$B$5:$B$60),WORKDAY($P$28,1+$N29,Holidays!$B$5:$B$60)) -> 46370 | P29: =IF($K29="N",WORKDAY($O29,-1,Holidays!$B$5:$B$60),IF($L29=0,$O29,WORKDAY($O29,$L29-1,Holidays!$B$5:$B$60))) -> 46367 | Q29: Not started | R29: =IF(AND($G29="HOLD",$K29="Y"),"■ HOLD: go/no-go. ","") | S29: Re-run the DealsDash appraisal with real costs. Walk away if it fails.
A30: A10 | B30: A Purchase & DD | C30: Exchange contracts (deposit paid) | D30: Solicitor | E30: Estate agent | H30: 0 | I30: 0 | J30: N | K30: =IF(AND(OR($E30="Both",$E30=$C$6),OR($F30="",IFERROR(INDEX($F$5:$F$13,MATCH($F30,$E$5:$E$13,0)),"Y")="Y")),"Y","N") -> N | L30: =IF($K30="N",0,IF(IF($C$6="Auction",$H30,$I30)=0,0,ROUNDUP(IF($C$6="Auction",$H30,$I30)*(1+IF($J30="Y",$C$10,0)),0))) -> 0 | M30: A9FS; A6FS | N30: 0 | O30: =MAX(WORKDAY($P$29,1+$N30,Holidays!$B$5:$B$60),WORKDAY($P$26,1+$N30,Holidays!$B$5:$B$60)) -> 46391 | P30: =IF($K30="N",WORKDAY($O30,-1,Holidays!$B$5:$B$60),IF($L30=0,$O30,WORKDAY($O30,$L30-1,Holidays!$B$5:$B$60))) -> 46380 | Q30: Not started | R30: =IF(AND($G30="HOLD",$K30="Y"),"■ HOLD: go/no-go. ","") | S30: Legally committed from here.
A31: A11 | B31: A Purchase & DD | C31: Lender's legal work, report on title, funds requested | D31: Solicitors | E31: Both | H31: 5 | I31: 5 | J31: N | K31: =IF(AND(OR($E31="Both",$E31=$C$6),OR($F31="",IFERROR(INDEX($F$5:$F$13,MATCH($F31,$E$5:$E$13,0)),"Y")="Y")),"Y","N") -> Y | L31: =IF($K31="N",0,IF(IF($C$6="Auction",$H31,$I31)=0,0,ROUNDUP(IF($C$6="Auction",$H31,$I31)*(1+IF($J31="Y",$C$10,0)),0))) -> 5 | M31: A6FS; A10FS | N31: 0 | O31: =MAX(WORKDAY($P$26,1+$N31,Holidays!$B$5:$B$60),WORKDAY($P$30,1+$N31,Holidays!$B$5:$B$60)) -> 46391 | P31: =IF($K31="N",WORKDAY($O31,-1,Holidays!$B$5:$B$60),IF($L31=0,$O31,WORKDAY($O31,$L31-1,Holidays!$B$5:$B$60))) -> 46395 | Q31: Not started | R31: =IF(AND($G31="HOLD",$K31="Y"),"■ HOLD: go/no-go. ","")
A32: A12 | B32: A Purchase & DD | C32: PURCHASE COMPLETION: keys released | D32: Solicitor | E32: Both | H32: 0 | I32: 0 | J32: N | K32: =IF(AND(OR($E32="Both",$E32=$C$6),OR($F32="",IFERROR(INDEX($F$5:$F$13,MATCH($F32,$E$5:$E$13,0)),"Y")="Y")),"Y","N") -> Y | L32: =IF($K32="N",0,IF(IF($C$6="Auction",$H32,$I32)=0,0,ROUNDUP(IF($C$6="Auction",$H32,$I32)*(1+IF($J32="Y",$C$10,0)),0))) -> 0 | M32: A1 (auction) / A10, A11 (agent) | N32: 0 | O32: =IF($C$6="Auction",WORKDAY($O$21+$C$8-1,1,Holidays!$B$5:$B$60),MAX(WORKDAY($P$30,$C$9,Holidays!$B$5:$B$60),WORKDAY($P$31,1,Holidays!$B$5:$B$60))) -> 46394 | P32: =IF($K32="N",WORKDAY($O32,-1,Holidays!$B$5:$B$60),IF($L32=0,$O32,WORKDAY($O32,$L32-1,Holidays!$B$5:$B$60))) -> 46394 | Q32: Not started | R32: =IF(AND($G32="HOLD",$K32="Y"),"■ HOLD: go/no-go. ","")&IF(AND($C$6="Auction",$P$31>$O32),"⚠ Finance not ready by auction completion: deposit at risk. ","") -> ⚠ Finance not ready by auction completion: deposit at risk. | S32: Auction: fixed by contract (usually 28 calendar days). Agent: exchange + C9 working days.
A33: B1 | B33: B Pre-start | C33: Builder schedule of works and measured scope | D33: Builder | E33: Both | H33: 3 | I33: 3 | J33: N | K33: =IF(AND(OR($E33="Both",$E33=$C$6),OR($F33="",IFERROR(INDEX($F$5:$F$13,MATCH($F33,$E$5:$E$13,0)),"Y")="Y")),"Y","N") -> Y | L33: =IF($K33="N",0,IF(IF($C$6="Auction",$H33,$I33)=0,0,ROUNDUP(IF($C$6="Auction",$H33,$I33)*(1+IF($J33="Y",$C$10,0)),0))) -> 3 | M33: A1FS; A8FS | N33: 0 | O33: =MAX(WORKDAY($P$21,1+$N33,Holidays!$B$5:$B$60),WORKDAY($P$28,1+$N33,Holidays!$B$5:$B$60)) -> 46370 | P33: =IF($K33="N",WORKDAY($O33,-1,Holidays!$B$5:$B$60),IF($L33=0,$O33,WORKDAY($O33,$L33-1,Holidays!$B$5:$B$60))) -> 46372 | Q33: Not started | R33: =IF(AND($G33="HOLD",$K33="Y"),"■ HOLD: go/no-go. ","") | S33: Auction: arrange access via auctioneer/seller, or use the pre-bid viewing scope.
A34: B2 | B34: B Pre-start | C34: Fixed-price quote(s) received; mentor review | D34: Builder / mentor | E34: Both | H34: 5 | I34: 5 | J34: N | K34: =IF(AND(OR($E34="Both",$E34=$C$6),OR($F34="",IFERROR(INDEX($F$5:$F$13,MATCH($F34,$E$5:$E$13,0)),"Y")="Y")),"Y","N") -> Y | L34: =IF($K34="N",0,IF(IF($C$6="Auction",$H34,$I34)=0,0,ROUNDUP(IF($C$6="Auction",$H34,$I34)*(1+IF($J34="Y",$C$10,0)),0))) -> 5 | M34: B1FS | N34: 0 | O34: =WORKDAY($P$33,1+$N34,Holidays!$B$5:$B$60) -> 46373 | P34: =IF($K34="N",WORKDAY($O34,-1,Holidays!$B$5:$B$60),IF($L34=0,$O34,WORKDAY($O34,$L34-1,Holidays!$B$5:$B$60))) -> 46379 | Q34: Not started | R34: =IF(AND($G34="HOLD",$K34="Y"),"■ HOLD: go/no-go. ","")
A35: B3 | B35: B Pre-start | C35: Sign contract: scope, stage payments, 5% retention; check insurance, verify CIS | D35: Paul | E35: Both | G35: HOLD | H35: 2 | I35: 2 | J35: N | K35: =IF(AND(OR($E35="Both",$E35=$C$6),OR($F35="",IFERROR(INDEX($F$5:$F$13,MATCH($F35,$E$5:$E$13,0)),"Y")="Y")),"Y","N") -> Y | L35: =IF($K35="N",0,IF(IF($C$6="Auction",$H35,$I35)=0,0,ROUNDUP(IF($C$6="Auction",$H35,$I35)*(1+IF($J35="Y",$C$10,0)),0))) -> 2 | M35: B2FS | N35: 0 | O35: =WORKDAY($P$34,1+$N35,Holidays!$B$5:$B$60) -> 46380 | P35: =IF($K35="N",WORKDAY($O35,-1,Holidays!$B$5:$B$60),IF($L35=0,$O35,WORKDAY($O35,$L35-1,Holidays!$B$5:$B$60))) -> 46391 | Q35: Not started | R35: =IF(AND($G35="HOLD",$K35="Y"),"■ HOLD: go/no-go. ","") -> ■ HOLD: go/no-go. | S35: No signed scope + price = no start.
A36: B4 | B36: B Pre-start | C36: Order long-lead items (kitchen, boiler, windows) | D36: Paul / builder | E36: Both | H36: 1 | I36: 1 | J36: N | K36: =IF(AND(OR($E36="Both",$E36=$C$6),OR($F36="",IFERROR(INDEX($F$5:$F$13,MATCH($F36,$E$5:$E$13,0)),"Y")="Y")),"Y","N") -> Y | L36: =IF($K36="N",0,IF(IF($C$6="Auction",$H36,$I36)=0,0,ROUNDUP(IF($C$6="Auction",$H36,$I36)*(1+IF($J36="Y",$C$10,0)),0))) -> 1 | M36: B3FS | N36: 0 | O36: =WORKDAY($P$35,1+$N36,Holidays!$B$5:$B$60) -> 46392 | P36: =IF($K36="N",WORKDAY($O36,-1,Holidays!$B$5:$B$60),IF($L36=0,$O36,WORKDAY($O36,$L36-1,Holidays!$B$5:$B$60))) -> 46392 | Q36: Not started | R36: =IF(AND($G36="HOLD",$K36="Y"),"■ HOLD: go/no-go. ","")
A37: B5 | B37: B Pre-start | C37: Long-lead delivery window | D37: Suppliers | E37: Both | H37: 15 | I37: 15 | J37: N | K37: =IF(AND(OR($E37="Both",$E37=$C$6),OR($F37="",IFERROR(INDEX($F$5:$F$13,MATCH($F37,$E$5:$E$13,0)),"Y")="Y")),"Y","N") -> Y | L37: =IF($K37="N",0,IF(IF($C$6="Auction",$H37,$I37)=0,0,ROUNDUP(IF($C$6="Auction",$H37,$I37)*(1+IF($J37="Y",$C$10,0)),0))) -> 15 | M37: B4FS | N37: 0 | O37: =WORKDAY($P$36,1+$N37,Holidays!$B$5:$B$60) -> 46393 | P37: =IF($K37="N",WORKDAY($O37,-1,Holidays!$B$5:$B$60),IF($L37=0,$O37,WORKDAY($O37,$L37-1,Holidays!$B$5:$B$60))) -> 46413 | Q37: Not started | R37: =IF(AND($G37="HOLD",$K37="Y"),"■ HOLD: go/no-go. ","") | S37: Typical 3 weeks; windows can be 4–6. Edit to supplier quote.
A38: B6 | B38: B Pre-start | C38: Asbestos refurbishment survey | D38: Surveyor | E38: Both | F38: Pre-2000 build | H38: 5 | I38: 5 | J38: N | K38: =IF(AND(OR($E38="Both",$E38=$C$6),OR($F38="",IFERROR(INDEX($F$5:$F$13,MATCH($F38,$E$5:$E$13,0)),"Y")="Y")),"Y","N") -> Y | L38: =IF($K38="N",0,IF(IF($C$6="Auction",$H38,$I38)=0,0,ROUNDUP(IF($C$6="Auction",$H38,$I38)*(1+IF($J38="Y",$C$10,0)),0))) -> 5 | M38: A12FS | N38: 0 | O38: =WORKDAY($P$32,1+$N38,Holidays!$B$5:$B$60) -> 46395 | P38: =IF($K38="N",WORKDAY($O38,-1,Holidays!$B$5:$B$60),IF($L38=0,$O38,WORKDAY($O38,$L38-1,Holidays!$B$5:$B$60))) -> 46401 | Q38: Not started | R38: =IF(AND($G38="HOLD",$K38="Y"),"■ HOLD: go/no-go. ","") | S38: Before any intrusive work on a pre-2000 property (HSE guidance — confirm with contractor).
A39: B7 | B39: B Pre-start | C39: Utilities and meter readings, council tax, change locks, skip, start photos | D39: Paul | E39: Both | H39: 1 | I39: 1 | J39: N | K39: =IF(AND(OR($E39="Both",$E39=$C$6),OR($F39="",IFERROR(INDEX($F$5:$F$13,MATCH($F39,$E$5:$E$13,0)),"Y")="Y")),"Y","N") -> Y | L39: =IF($K39="N",0,IF(IF($C$6="Auction",$H39,$I39)=0,0,ROUNDUP(IF($C$6="Auction",$H39,$I39)*(1+IF($J39="Y",$C$10,0)),0))) -> 1 | M39: A12FS | N39: 0 | O39: =WORKDAY($P$32,1+$N39,Holidays!$B$5:$B$60) -> 46395 | P39: =IF($K39="N",WORKDAY($O39,-1,Holidays!$B$5:$B$60),IF($L39=0,$O39,WORKDAY($O39,$L39-1,Holidays!$B$5:$B$60))) -> 46395 | Q39: Not started | R39: =IF(AND($G39="HOLD",$K39="Y"),"■ HOLD: go/no-go. ","")
A40: C1 | B40: C Strip-out & structure | C40: Strip-out: kitchen, bathroom, flooring, blown plaster | D40: Builder | E40: Both | H40: 4 | I40: 4 | J40: Y | K40: =IF(AND(OR($E40="Both",$E40=$C$6),OR($F40="",IFERROR(INDEX($F$5:$F$13,MATCH($F40,$E$5:$E$13,0)),"Y")="Y")),"Y","N") -> Y | L40: =IF($K40="N",0,IF(IF($C$6="Auction",$H40,$I40)=0,0,ROUNDUP(IF($C$6="Auction",$H40,$I40)*(1+IF($J40="Y",$C$10,0)),0))) -> 5 | M40: B7FS; B6FS; B3FS | N40: 0 | O40: =MAX(WORKDAY($P$39,1+$N40,Holidays!$B$5:$B$60),WORKDAY($P$38,1+$N40,Holidays!$B$5:$B$60),WORKDAY($P$35,1+$N40,Holidays!$B$5:$B$60)) -> 46402 | P40: =IF($K40="N",WORKDAY($O40,-1,Holidays!$B$5:$B$60),IF($L40=0,$O40,WORKDAY($O40,$L40-1,Holidays!$B$5:$B$60))) -> 46408 | Q40: Not started | R40: =IF(AND($G40="HOLD",$K40="Y"),"■ HOLD: go/no-go. ","")
A41: C2 | B41: C Strip-out & structure | C41: Opening-up inspection; update costs in DealsDash | D41: Paul + builder | E41: Both | G41: HOLD | H41: 1 | I41: 1 | J41: N | K41: =IF(AND(OR($E41="Both",$E41=$C$6),OR($F41="",IFERROR(INDEX($F$5:$F$13,MATCH($F41,$E$5:$E$13,0)),"Y")="Y")),"Y","N") -> Y | L41: =IF($K41="N",0,IF(IF($C$6="Auction",$H41,$I41)=0,0,ROUNDUP(IF($C$6="Auction",$H41,$I41)*(1+IF($J41="Y",$C$10,0)),0))) -> 1 | M41: C1FS | N41: 0 | O41: =WORKDAY($P$40,1+$N41,Holidays!$B$5:$B$60) -> 46409 | P41: =IF($K41="N",WORKDAY($O41,-1,Holidays!$B$5:$B$60),IF($L41=0,$O41,WORKDAY($O41,$L41-1,Holidays!$B$5:$B$60))) -> 46409 | Q41: Not started | R41: =IF(AND($G41="HOLD",$K41="Y"),"■ HOLD: go/no-go. ","") -> ■ HOLD: go/no-go. | S41: Hidden defects show here. Re-check profit vs target before committing more spend.
A42: C3 | B42: C Strip-out & structure | C42: Structural works (engineer design + Building Control notice) | D42: Builder / engineer | E42: Both | F42: Structural | H42: 5 | I42: 5 | J42: Y | K42: =IF(AND(OR($E42="Both",$E42=$C$6),OR($F42="",IFERROR(INDEX($F$5:$F$13,MATCH($F42,$E$5:$E$13,0)),"Y")="Y")),"Y","N") -> N | L42: =IF($K42="N",0,IF(IF($C$6="Auction",$H42,$I42)=0,0,ROUNDUP(IF($C$6="Auction",$H42,$I42)*(1+IF($J42="Y",$C$10,0)),0))) -> 0 | M42: C2FS | N42: 0 | O42: =WORKDAY($P$41,1+$N42,Holidays!$B$5:$B$60) -> 46412 | P42: =IF($K42="N",WORKDAY($O42,-1,Holidays!$B$5:$B$60),IF($L42=0,$O42,WORKDAY($O42,$L42-1,Holidays!$B$5:$B$60))) -> 46409 | Q42: Not started | R42: =IF(AND($G42="HOLD",$K42="Y"),"■ HOLD: go/no-go. ","")
A43: C4 | B43: C Strip-out & structure | C43: Damp-proofing / timber treatment | D43: Specialist | E43: Both | F43: Damp/timber | H43: 3 | I43: 3 | J43: Y | K43: =IF(AND(OR($E43="Both",$E43=$C$6),OR($F43="",IFERROR(INDEX($F$5:$F$13,MATCH($F43,$E$5:$E$13,0)),"Y")="Y")),"Y","N") -> Y | L43: =IF($K43="N",0,IF(IF($C$6="Auction",$H43,$I43)=0,0,ROUNDUP(IF($C$6="Auction",$H43,$I43)*(1+IF($J43="Y",$C$10,0)),0))) -> 4 | M43: C2FS | N43: 0 | O43: =WORKDAY($P$41,1+$N43,Holidays!$B$5:$B$60) -> 46412 | P43: =IF($K43="N",WORKDAY($O43,-1,Holidays!$B$5:$B$60),IF($L43=0,$O43,WORKDAY($O43,$L43-1,Holidays!$B$5:$B$60))) -> 46415 | Q43: Not started | R43: =IF(AND($G43="HOLD",$K43="Y"),"■ HOLD: go/no-go. ","") | S43: Get the guarantee for the sale pack.
A44: C5 | B44: C Strip-out & structure | C44: Roof and external repairs (roof, gutters, pointing, render) | D44: Roofer / builder | E44: Both | F44: Roof/external | H44: 8 | I44: 8 | J44: Y | K44: =IF(AND(OR($E44="Both",$E44=$C$6),OR($F44="",IFERROR(INDEX($F$5:$F$13,MATCH($F44,$E$5:$E$13,0)),"Y")="Y")),"Y","N") -> N | L44: =IF($K44="N",0,IF(IF($C$6="Auction",$H44,$I44)=0,0,ROUNDUP(IF($C$6="Auction",$H44,$I44)*(1+IF($J44="Y",$C$10,0)),0))) -> 0 | M44: C2FS | N44: 0 | O44: =WORKDAY($P$41,1+$N44,Holidays!$B$5:$B$60) -> 46412 | P44: =IF($K44="N",WORKDAY($O44,-1,Holidays!$B$5:$B$60),IF($L44=0,$O44,WORKDAY($O44,$L44-1,Holidays!$B$5:$B$60))) -> 46409 | Q44: Not started | R44: =IF(AND($G44="HOLD",$K44="Y"),"■ HOLD: go/no-go. ","")&IF(AND($K44="Y",OR(MONTH($O44)>=11,MONTH($O44)<=2)),"⚠ External work in Nov–Feb: weather risk. ","")
A45: C6 | B45: C Strip-out & structure | C45: Windows and external doors fitted | D45: Installer | E45: Both | F45: Windows/doors | H45: 3 | I45: 3 | J45: Y | K45: =IF(AND(OR($E45="Both",$E45=$C$6),OR($F45="",IFERROR(INDEX($F$5:$F$13,MATCH($F45,$E$5:$E$13,0)),"Y")="Y")),"Y","N") -> N | L45: =IF($K45="N",0,IF(IF($C$6="Auction",$H45,$I45)=0,0,ROUNDUP(IF($C$6="Auction",$H45,$I45)*(1+IF($J45="Y",$C$10,0)),0))) -> 0 | M45: C2FS; B5FS | N45: 0 | O45: =MAX(WORKDAY($P$41,1+$N45,Holidays!$B$5:$B$60),WORKDAY($P$37,1+$N45,Holidays!$B$5:$B$60)) -> 46414 | P45: =IF($K45="N",WORKDAY($O45,-1,Holidays!$B$5:$B$60),IF($L45=0,$O45,WORKDAY($O45,$L45-1,Holidays!$B$5:$B$60))) -> 46413 | Q45: Not started | R45: =IF(AND($G45="HOLD",$K45="Y"),"■ HOLD: go/no-go. ","")&IF(AND($K45="Y",OR(MONTH($O45)>=11,MONTH($O45)<=2)),"⚠ External work in Nov–Feb: weather risk. ","") | S45: Keep FENSA certificate.
A46: D1 | B46: D First fix | C46: Electrical first fix (rewire) | D46: Electrician | E46: Both | F46: Rewire | H46: 4 | I46: 4 | J46: Y | K46: =IF(AND(OR($E46="Both",$E46=$C$6),OR($F46="",IFERROR(INDEX($F$5:$F$13,MATCH($F46,$E$5:$E$13,0)),"Y")="Y")),"Y","N") -> Y | L46: =IF($K46="N",0,IF(IF($C$6="Auction",$H46,$I46)=0,0,ROUNDUP(IF($C$6="Auction",$H46,$I46)*(1+IF($J46="Y",$C$10,0)),0))) -> 5 | M46: C3FS; C4FS | N46: 0 | O46: =MAX(WORKDAY($P$42,1+$N46,Holidays!$B$5:$B$60),WORKDAY($P$43,1+$N46,Holidays!$B$5:$B$60)) -> 46416 | P46: =IF($K46="N",WORKDAY($O46,-1,Holidays!$B$5:$B$60),IF($L46=0,$O46,WORKDAY($O46,$L46-1,Holidays!$B$5:$B$60))) -> 46422 | Q46: Not started | R46: =IF(AND($G46="HOLD",$K46="Y"),"■ HOLD: go/no-go. ","")
A47: D2 | B47: D First fix | C47: Plumbing and heating first fix | D47: Plumber | E47: Both | F47: Heating/boiler | H47: 4 | I47: 4 | J47: Y | K47: =IF(AND(OR($E47="Both",$E47=$C$6),OR($F47="",IFERROR(INDEX($F$5:$F$13,MATCH($F47,$E$5:$E$13,0)),"Y")="Y")),"Y","N") -> Y | L47: =IF($K47="N",0,IF(IF($C$6="Auction",$H47,$I47)=0,0,ROUNDUP(IF($C$6="Auction",$H47,$I47)*(1+IF($J47="Y",$C$10,0)),0))) -> 5 | M47: C3FS; C4FS | N47: 1 | O47: =MAX(WORKDAY($P$42,1+$N47,Holidays!$B$5:$B$60),WORKDAY($P$43,1+$N47,Holidays!$B$5:$B$60)) -> 46419 | P47: =IF($K47="N",WORKDAY($O47,-1,Holidays!$B$5:$B$60),IF($L47=0,$O47,WORKDAY($O47,$L47-1,Holidays!$B$5:$B$60))) -> 46423 | Q47: Not started | R47: =IF(AND($G47="HOLD",$K47="Y"),"■ HOLD: go/no-go. ","") | S47: Starts 1 day after electrics to share the site.
A48: D3 | B48: D First fix | C48: Joinery first fix (stud walls, linings) | D48: Carpenter | E48: Both | H48: 3 | I48: 3 | J48: Y | K48: =IF(AND(OR($E48="Both",$E48=$C$6),OR($F48="",IFERROR(INDEX($F$5:$F$13,MATCH($F48,$E$5:$E$13,0)),"Y")="Y")),"Y","N") -> Y | L48: =IF($K48="N",0,IF(IF($C$6="Auction",$H48,$I48)=0,0,ROUNDUP(IF($C$6="Auction",$H48,$I48)*(1+IF($J48="Y",$C$10,0)),0))) -> 4 | M48: C3FS; C4FS | N48: 0 | O48: =MAX(WORKDAY($P$42,1+$N48,Holidays!$B$5:$B$60),WORKDAY($P$43,1+$N48,Holidays!$B$5:$B$60)) -> 46416 | P48: =IF($K48="N",WORKDAY($O48,-1,Holidays!$B$5:$B$60),IF($L48=0,$O48,WORKDAY($O48,$L48-1,Holidays!$B$5:$B$60))) -> 46421 | Q48: Not started | R48: =IF(AND($G48="HOLD",$K48="Y"),"■ HOLD: go/no-go. ","")
A49: D4 | B49: D First fix | C49: First-fix check before boarding (electrician / Building Control if notifiable) | D49: Builder | E49: Both | G49: HOLD | H49: 1 | I49: 1 | J49: N | K49: =IF(AND(OR($E49="Both",$E49=$C$6),OR($F49="",IFERROR(INDEX($F$5:$F$13,MATCH($F49,$E$5:$E$13,0)),"Y")="Y")),"Y","N") -> Y | L49: =IF($K49="N",0,IF(IF($C$6="Auction",$H49,$I49)=0,0,ROUNDUP(IF($C$6="Auction",$H49,$I49)*(1+IF($J49="Y",$C$10,0)),0))) -> 1 | M49: D1FS; D2FS; D3FS | N49: 0 | O49: =MAX(WORKDAY($P$46,1+$N49,Holidays!$B$5:$B$60),WORKDAY($P$47,1+$N49,Holidays!$B$5:$B$60),WORKDAY($P$48,1+$N49,Holidays!$B$5:$B$60)) -> 46426 | P49: =IF($K49="N",WORKDAY($O49,-1,Holidays!$B$5:$B$60),IF($L49=0,$O49,WORKDAY($O49,$L49-1,Holidays!$B$5:$B$60))) -> 46426 | Q49: Not started | R49: =IF(AND($G49="HOLD",$K49="Y"),"■ HOLD: go/no-go. ","") -> ■ HOLD: go/no-go. | S49: Photograph every wall before boarding.
A50: E1 | B50: E Plaster | C50: Board, plaster and skim | D50: Plasterer | E50: Both | H50: 6 | I50: 6 | J50: Y | K50: =IF(AND(OR($E50="Both",$E50=$C$6),OR($F50="",IFERROR(INDEX($F$5:$F$13,MATCH($F50,$E$5:$E$13,0)),"Y")="Y")),"Y","N") -> Y | L50: =IF($K50="N",0,IF(IF($C$6="Auction",$H50,$I50)=0,0,ROUNDUP(IF($C$6="Auction",$H50,$I50)*(1+IF($J50="Y",$C$10,0)),0))) -> 7 | M50: D4FS; C5FS; C6FS | N50: 0 | O50: =MAX(WORKDAY($P$49,1+$N50,Holidays!$B$5:$B$60),WORKDAY($P$44,1+$N50,Holidays!$B$5:$B$60),WORKDAY($P$45,1+$N50,Holidays!$B$5:$B$60)) -> 46427 | P50: =IF($K50="N",WORKDAY($O50,-1,Holidays!$B$5:$B$60),IF($L50=0,$O50,WORKDAY($O50,$L50-1,Holidays!$B$5:$B$60))) -> 46435 | Q50: Not started | R50: =IF(AND($G50="HOLD",$K50="Y"),"■ HOLD: go/no-go. ","") | S50: Roof watertight and windows in first.
A51: E2 | B51: E Plaster | C51: Drying out (winter allowance added automatically Nov–Feb) | D51: — | E51: Both | H51: 5 | I51: 5 | J51: N | K51: =IF(AND(OR($E51="Both",$E51=$C$6),OR($F51="",IFERROR(INDEX($F$5:$F$13,MATCH($F51,$E$5:$E$13,0)),"Y")="Y")),"Y","N") -> Y | L51: =IF($K51="N",0,IF(IF($C$6="Auction",$H51,$I51)=0,0,ROUNDUP(IF($C$6="Auction",$H51,$I51)*(1+IF($J51="Y",$C$10,0)),0)+IF(OR(MONTH($O51)>=11,MONTH($O51)<=2),$C$11,0))) -> 8 | M51: E1FS | N51: 0 | O51: =WORKDAY($P$50,1+$N51,Holidays!$B$5:$B$60) -> 46436 | P51: =IF($K51="N",WORKDAY($O51,-1,Holidays!$B$5:$B$60),IF($L51=0,$O51,WORKDAY($O51,$L51-1,Holidays!$B$5:$B$60))) -> 46447 | Q51: Not started | R51: =IF(AND($G51="HOLD",$K51="Y"),"■ HOLD: go/no-go. ","")&IF(OR(MONTH($O51)>=11,MONTH($O51)<=2),"Winter drying allowance added. ","") -> Winter drying allowance added. | S51: Heat + dehumidifiers. Painting too early = cracking and bloom.
A52: E3 | B52: E Plaster | C52: Mist coat | D52: Decorator | E52: Both | H52: 2 | I52: 2 | J52: Y | K52: =IF(AND(OR($E52="Both",$E52=$C$6),OR($F52="",IFERROR(INDEX($F$5:$F$13,MATCH($F52,$E$5:$E$13,0)),"Y")="Y")),"Y","N") -> Y | L52: =IF($K52="N",0,IF(IF($C$6="Auction",$H52,$I52)=0,0,ROUNDUP(IF($C$6="Auction",$H52,$I52)*(1+IF($J52="Y",$C$10,0)),0))) -> 3 | M52: E2FS | N52: 0 | O52: =WORKDAY($P$51,1+$N52,Holidays!$B$5:$B$60) -> 46448 | P52: =IF($K52="N",WORKDAY($O52,-1,Holidays!$B$5:$B$60),IF($L52=0,$O52,WORKDAY($O52,$L52-1,Holidays!$B$5:$B$60))) -> 46450 | Q52: Not started | R52: =IF(AND($G52="HOLD",$K52="Y"),"■ HOLD: go/no-go. ","")
A53: F1 | B53: F Second fix & finish | C53: Kitchen fit | D53: Kitchen fitter | E53: Both | F53: Kitchen | H53: 4 | I53: 4 | J53: Y | K53: =IF(AND(OR($E53="Both",$E53=$C$6),OR($F53="",IFERROR(INDEX($F$5:$F$13,MATCH($F53,$E$5:$E$13,0)),"Y")="Y")),"Y","N") -> Y | L53: =IF($K53="N",0,IF(IF($C$6="Auction",$H53,$I53)=0,0,ROUNDUP(IF($C$6="Auction",$H53,$I53)*(1+IF($J53="Y",$C$10,0)),0))) -> 5 | M53: E3FS; B5FS | N53: 0 | O53: =MAX(WORKDAY($P$52,1+$N53,Holidays!$B$5:$B$60),WORKDAY($P$37,1+$N53,Holidays!$B$5:$B$60)) -> 46451 | P53: =IF($K53="N",WORKDAY($O53,-1,Holidays!$B$5:$B$60),IF($L53=0,$O53,WORKDAY($O53,$L53-1,Holidays!$B$5:$B$60))) -> 46457 | Q53: Not started | R53: =IF(AND($G53="HOLD",$K53="Y"),"■ HOLD: go/no-go. ","")
A54: F2 | B54: F Second fix & finish | C54: Bathroom fit and tiling | D54: Plumber / tiler | E54: Both | F54: Bathroom | H54: 5 | I54: 5 | J54: Y | K54: =IF(AND(OR($E54="Both",$E54=$C$6),OR($F54="",IFERROR(INDEX($F$5:$F$13,MATCH($F54,$E$5:$E$13,0)),"Y")="Y")),"Y","N") -> Y | L54: =IF($K54="N",0,IF(IF($C$6="Auction",$H54,$I54)=0,0,ROUNDUP(IF($C$6="Auction",$H54,$I54)*(1+IF($J54="Y",$C$10,0)),0))) -> 6 | M54: E3FS | N54: 0 | O54: =WORKDAY($P$52,1+$N54,Holidays!$B$5:$B$60) -> 46451 | P54: =IF($K54="N",WORKDAY($O54,-1,Holidays!$B$5:$B$60),IF($L54=0,$O54,WORKDAY($O54,$L54-1,Holidays!$B$5:$B$60))) -> 46458 | Q54: Not started | R54: =IF(AND($G54="HOLD",$K54="Y"),"■ HOLD: go/no-go. ","")
A55: F3 | B55: F Second fix & finish | C55: Electrical second fix and testing | D55: Electrician | E55: Both | H55: 2 | I55: 2 | J55: Y | K55: =IF(AND(OR($E55="Both",$E55=$C$6),OR($F55="",IFERROR(INDEX($F$5:$F$13,MATCH($F55,$E$5:$E$13,0)),"Y")="Y")),"Y","N") -> Y | L55: =IF($K55="N",0,IF(IF($C$6="Auction",$H55,$I55)=0,0,ROUNDUP(IF($C$6="Auction",$H55,$I55)*(1+IF($J55="Y",$C$10,0)),0))) -> 3 | M55: F1FS; F2FS | N55: 0 | O55: =MAX(WORKDAY($P$53,1+$N55,Holidays!$B$5:$B$60),WORKDAY($P$54,1+$N55,Holidays!$B$5:$B$60)) -> 46461 | P55: =IF($K55="N",WORKDAY($O55,-1,Holidays!$B$5:$B$60),IF($L55=0,$O55,WORKDAY($O55,$L55-1,Holidays!$B$5:$B$60))) -> 46463 | Q55: Not started | R55: =IF(AND($G55="HOLD",$K55="Y"),"■ HOLD: go/no-go. ","")
A56: F4 | B56: F Second fix & finish | C56: Plumbing / heating second fix; boiler commissioned | D56: Plumber / Gas Safe | E56: Both | H56: 2 | I56: 2 | J56: Y | K56: =IF(AND(OR($E56="Both",$E56=$C$6),OR($F56="",IFERROR(INDEX($F$5:$F$13,MATCH($F56,$E$5:$E$13,0)),"Y")="Y")),"Y","N") -> Y | L56: =IF($K56="N",0,IF(IF($C$6="Auction",$H56,$I56)=0,0,ROUNDUP(IF($C$6="Auction",$H56,$I56)*(1+IF($J56="Y",$C$10,0)),0))) -> 3 | M56: F1FS; F2FS | N56: 0 | O56: =MAX(WORKDAY($P$53,1+$N56,Holidays!$B$5:$B$60),WORKDAY($P$54,1+$N56,Holidays!$B$5:$B$60)) -> 46461 | P56: =IF($K56="N",WORKDAY($O56,-1,Holidays!$B$5:$B$60),IF($L56=0,$O56,WORKDAY($O56,$L56-1,Holidays!$B$5:$B$60))) -> 46463 | Q56: Not started | R56: =IF(AND($G56="HOLD",$K56="Y"),"■ HOLD: go/no-go. ","")
A57: F5 | B57: F Second fix & finish | C57: Joinery second fix (doors, skirting, architrave) | D57: Carpenter | E57: Both | H57: 3 | I57: 3 | J57: Y | K57: =IF(AND(OR($E57="Both",$E57=$C$6),OR($F57="",IFERROR(INDEX($F$5:$F$13,MATCH($F57,$E$5:$E$13,0)),"Y")="Y")),"Y","N") -> Y | L57: =IF($K57="N",0,IF(IF($C$6="Auction",$H57,$I57)=0,0,ROUNDUP(IF($C$6="Auction",$H57,$I57)*(1+IF($J57="Y",$C$10,0)),0))) -> 4 | M57: E3FS | N57: 0 | O57: =WORKDAY($P$52,1+$N57,Holidays!$B$5:$B$60) -> 46451 | P57: =IF($K57="N",WORKDAY($O57,-1,Holidays!$B$5:$B$60),IF($L57=0,$O57,WORKDAY($O57,$L57-1,Holidays!$B$5:$B$60))) -> 46456 | Q57: Not started | R57: =IF(AND($G57="HOLD",$K57="Y"),"■ HOLD: go/no-go. ","")
A58: F6 | B58: F Second fix & finish | C58: Decoration | D58: Decorator | E58: Both | H58: 6 | I58: 6 | J58: Y | K58: =IF(AND(OR($E58="Both",$E58=$C$6),OR($F58="",IFERROR(INDEX($F$5:$F$13,MATCH($F58,$E$5:$E$13,0)),"Y")="Y")),"Y","N") -> Y | L58: =IF($K58="N",0,IF(IF($C$6="Auction",$H58,$I58)=0,0,ROUNDUP(IF($C$6="Auction",$H58,$I58)*(1+IF($J58="Y",$C$10,0)),0))) -> 7 | M58: F3FS; F4FS; F5FS | N58: 0 | O58: =MAX(WORKDAY($P$55,1+$N58,Holidays!$B$5:$B$60),WORKDAY($P$56,1+$N58,Holidays!$B$5:$B$60),WORKDAY($P$57,1+$N58,Holidays!$B$5:$B$60)) -> 46464 | P58: =IF($K58="N",WORKDAY($O58,-1,Holidays!$B$5:$B$60),IF($L58=0,$O58,WORKDAY($O58,$L58-1,Holidays!$B$5:$B$60))) -> 46476 | Q58: Not started | R58: =IF(AND($G58="HOLD",$K58="Y"),"■ HOLD: go/no-go. ","")
A59: F7 | B59: F Second fix & finish | C59: Flooring | D59: Flooring fitter | E59: Both | H59: 2 | I59: 2 | J59: Y | K59: =IF(AND(OR($E59="Both",$E59=$C$6),OR($F59="",IFERROR(INDEX($F$5:$F$13,MATCH($F59,$E$5:$E$13,0)),"Y")="Y")),"Y","N") -> Y | L59: =IF($K59="N",0,IF(IF($C$6="Auction",$H59,$I59)=0,0,ROUNDUP(IF($C$6="Auction",$H59,$I59)*(1+IF($J59="Y",$C$10,0)),0))) -> 3 | M59: F6FS | N59: 0 | O59: =WORKDAY($P$58,1+$N59,Holidays!$B$5:$B$60) -> 46477 | P59: =IF($K59="N",WORKDAY($O59,-1,Holidays!$B$5:$B$60),IF($L59=0,$O59,WORKDAY($O59,$L59-1,Holidays!$B$5:$B$60))) -> 46479 | Q59: Not started | R59: =IF(AND($G59="HOLD",$K59="Y"),"■ HOLD: go/no-go. ","")
A60: F8 | B60: F Second fix & finish | C60: Kerb appeal: front door, paint, garden tidy | D60: Builder | E60: Both | H60: 2 | I60: 2 | J60: Y | K60: =IF(AND(OR($E60="Both",$E60=$C$6),OR($F60="",IFERROR(INDEX($F$5:$F$13,MATCH($F60,$E$5:$E$13,0)),"Y")="Y")),"Y","N") -> Y | L60: =IF($K60="N",0,IF(IF($C$6="Auction",$H60,$I60)=0,0,ROUNDUP(IF($C$6="Auction",$H60,$I60)*(1+IF($J60="Y",$C$10,0)),0))) -> 3 | M60: F6FS | N60: 0 | O60: =WORKDAY($P$58,1+$N60,Holidays!$B$5:$B$60) -> 46477 | P60: =IF($K60="N",WORKDAY($O60,-1,Holidays!$B$5:$B$60),IF($L60=0,$O60,WORKDAY($O60,$L60-1,Holidays!$B$5:$B$60))) -> 46479 | Q60: Not started | R60: =IF(AND($G60="HOLD",$K60="Y"),"■ HOLD: go/no-go. ","")&IF(AND($K60="Y",OR(MONTH($O60)>=11,MONTH($O60)<=2)),"⚠ External work in Nov–Feb: weather risk. ","") | S60: Training rule: £1 of refurb should add £3 of value.
A61: G1 | B61: G Sign-off | C61: Certificates: EIC (Part P), Gas Safe / Building Regs, FENSA, Building Control completion | D61: Trades | E61: Both | H61: 3 | I61: 3 | J61: N | K61: =IF(AND(OR($E61="Both",$E61=$C$6),OR($F61="",IFERROR(INDEX($F$5:$F$13,MATCH($F61,$E$5:$E$13,0)),"Y")="Y")),"Y","N") -> Y | L61: =IF($K61="N",0,IF(IF($C$6="Auction",$H61,$I61)=0,0,ROUNDUP(IF($C$6="Auction",$H61,$I61)*(1+IF($J61="Y",$C$10,0)),0))) -> 3 | M61: F3FS; F4FS | N61: 0 | O61: =MAX(WORKDAY($P$55,1+$N61,Holidays!$B$5:$B$60),WORKDAY($P$56,1+$N61,Holidays!$B$5:$B$60)) -> 46464 | P61: =IF($K61="N",WORKDAY($O61,-1,Holidays!$B$5:$B$60),IF($L61=0,$O61,WORKDAY($O61,$L61-1,Holidays!$B$5:$B$60))) -> 46468 | Q61: Not started | R61: =IF(AND($G61="HOLD",$K61="Y"),"■ HOLD: go/no-go. ","") | S61: Buyer's solicitor will ask for every one. No certs = delayed exchange.
A62: G2 | B62: G Sign-off | C62: Snagging walk-round and fixes | D62: Paul + builder | E62: Both | H62: 3 | I62: 3 | J62: N | K62: =IF(AND(OR($E62="Both",$E62=$C$6),OR($F62="",IFERROR(INDEX($F$5:$F$13,MATCH($F62,$E$5:$E$13,0)),"Y")="Y")),"Y","N") -> Y | L62: =IF($K62="N",0,IF(IF($C$6="Auction",$H62,$I62)=0,0,ROUNDUP(IF($C$6="Auction",$H62,$I62)*(1+IF($J62="Y",$C$10,0)),0))) -> 3 | M62: F7FS; F8FS | N62: 0 | O62: =MAX(WORKDAY($P$59,1+$N62,Holidays!$B$5:$B$60),WORKDAY($P$60,1+$N62,Holidays!$B$5:$B$60)) -> 46482 | P62: =IF($K62="N",WORKDAY($O62,-1,Holidays!$B$5:$B$60),IF($L62=0,$O62,WORKDAY($O62,$L62-1,Holidays!$B$5:$B$60))) -> 46484 | Q62: Not started | R62: =IF(AND($G62="HOLD",$K62="Y"),"■ HOLD: go/no-go. ","")
A63: G3 | B63: G Sign-off | C63: PRACTICAL COMPLETION: stage payment (5% retention held) | D63: Paul | E63: Both | G63: HOLD | H63: 0 | I63: 0 | J63: N | K63: =IF(AND(OR($E63="Both",$E63=$C$6),OR($F63="",IFERROR(INDEX($F$5:$F$13,MATCH($F63,$E$5:$E$13,0)),"Y")="Y")),"Y","N") -> Y | L63: =IF($K63="N",0,IF(IF($C$6="Auction",$H63,$I63)=0,0,ROUNDUP(IF($C$6="Auction",$H63,$I63)*(1+IF($J63="Y",$C$10,0)),0))) -> 0 | M63: G2FS | N63: 0 | O63: =WORKDAY($P$62,1+$N63,Holidays!$B$5:$B$60) -> 46485 | P63: =IF($K63="N",WORKDAY($O63,-1,Holidays!$B$5:$B$60),IF($L63=0,$O63,WORKDAY($O63,$L63-1,Holidays!$B$5:$B$60))) -> 46485 | Q63: Not started | R63: =IF(AND($G63="HOLD",$K63="Y"),"■ HOLD: go/no-go. ","") -> ■ HOLD: go/no-go. | S63: Sign off only when the snag list is clear.
A64: G4 | B64: G Sign-off | C64: EPC commissioned | D64: Assessor | E64: Both | H64: 2 | I64: 2 | J64: N | K64: =IF(AND(OR($E64="Both",$E64=$C$6),OR($F64="",IFERROR(INDEX($F$5:$F$13,MATCH($F64,$E$5:$E$13,0)),"Y")="Y")),"Y","N") -> Y | L64: =IF($K64="N",0,IF(IF($C$6="Auction",$H64,$I64)=0,0,ROUNDUP(IF($C$6="Auction",$H64,$I64)*(1+IF($J64="Y",$C$10,0)),0))) -> 2 | M64: G2FS | N64: 0 | O64: =WORKDAY($P$62,1+$N64,Holidays!$B$5:$B$60) -> 46485 | P64: =IF($K64="N",WORKDAY($O64,-1,Holidays!$B$5:$B$60),IF($L64=0,$O64,WORKDAY($O64,$L64-1,Holidays!$B$5:$B$60))) -> 46486 | Q64: Not started | R64: =IF(AND($G64="HOLD",$K64="Y"),"■ HOLD: go/no-go. ","") | S64: Must be commissioned before marketing.
A65: G5 | B65: G Sign-off | C65: Deep clean, staging, photos and floorplan | D65: Paul | E65: Both | H65: 3 | I65: 3 | J65: N | K65: =IF(AND(OR($E65="Both",$E65=$C$6),OR($F65="",IFERROR(INDEX($F$5:$F$13,MATCH($F65,$E$5:$E$13,0)),"Y")="Y")),"Y","N") -> Y | L65: =IF($K65="N",0,IF(IF($C$6="Auction",$H65,$I65)=0,0,ROUNDUP(IF($C$6="Auction",$H65,$I65)*(1+IF($J65="Y",$C$10,0)),0))) -> 3 | M65: G2FS | N65: 0 | O65: =WORKDAY($P$62,1+$N65,Holidays!$B$5:$B$60) -> 46485 | P65: =IF($K65="N",WORKDAY($O65,-1,Holidays!$B$5:$B$60),IF($L65=0,$O65,WORKDAY($O65,$L65-1,Holidays!$B$5:$B$60))) -> 46489 | Q65: Not started | R65: =IF(AND($G65="HOLD",$K65="Y"),"■ HOLD: go/no-go. ","")
A66: H1 | B66: H Sale & close-out | C66: Three agent valuations; instruct agent | D66: Paul | E66: Both | H66: 3 | I66: 3 | J66: N | K66: =IF(AND(OR($E66="Both",$E66=$C$6),OR($F66="",IFERROR(INDEX($F$5:$F$13,MATCH($F66,$E$5:$E$13,0)),"Y")="Y")),"Y","N") -> Y | L66: =IF($K66="N",0,IF(IF($C$6="Auction",$H66,$I66)=0,0,ROUNDUP(IF($C$6="Auction",$H66,$I66)*(1+IF($J66="Y",$C$10,0)),0))) -> 3 | M66: G2SS | N66: 0 | O66: =WORKDAY($O$62,$N66,Holidays!$B$5:$B$60) -> 46482 | P66: =IF($K66="N",WORKDAY($O66,-1,Holidays!$B$5:$B$60),IF($L66=0,$O66,WORKDAY($O66,$L66-1,Holidays!$B$5:$B$60))) -> 46484 | Q66: Not started | R66: =IF(AND($G66="HOLD",$K66="Y"),"■ HOLD: go/no-go. ","") | S66: Book during snagging.
A67: H2 | B67: H Sale & close-out | C67: LISTED on portals | D67: Agent | E67: Both | H67: 0 | I67: 0 | J67: N | K67: =IF(AND(OR($E67="Both",$E67=$C$6),OR($F67="",IFERROR(INDEX($F$5:$F$13,MATCH($F67,$E$5:$E$13,0)),"Y")="Y")),"Y","N") -> Y | L67: =IF($K67="N",0,IF(IF($C$6="Auction",$H67,$I67)=0,0,ROUNDUP(IF($C$6="Auction",$H67,$I67)*(1+IF($J67="Y",$C$10,0)),0))) -> 0 | M67: H1FS; G4FS; G5FS | N67: 0 | O67: =MAX(WORKDAY($P$66,1+$N67,Holidays!$B$5:$B$60),WORKDAY($P$64,1+$N67,Holidays!$B$5:$B$60),WORKDAY($P$65,1+$N67,Holidays!$B$5:$B$60)) -> 46490 | P67: =IF($K67="N",WORKDAY($O67,-1,Holidays!$B$5:$B$60),IF($L67=0,$O67,WORKDAY($O67,$L67-1,Holidays!$B$5:$B$60))) -> 46490 | Q67: Not started | R67: =IF(AND($G67="HOLD",$K67="Y"),"■ HOLD: go/no-go. ","")&IF(OR(MONTH($O67)=8,MONTH($O67)=11,MONTH($O67)=12),"⚠ Listing in a slow month (Aug/Nov/Dec). ","")
A68: H3 | B68: H Sale & close-out | C68: Viewings → sale agreed | D68: Agent | E68: Both | H68: =$C$12 -> 30 | I68: =$C$12 -> 30 | J68: N | K68: =IF(AND(OR($E68="Both",$E68=$C$6),OR($F68="",IFERROR(INDEX($F$5:$F$13,MATCH($F68,$E$5:$E$13,0)),"Y")="Y")),"Y","N") -> Y | L68: =IF($K68="N",0,IF(IF($C$6="Auction",$H68,$I68)=0,0,ROUNDUP(IF($C$6="Auction",$H68,$I68)*(1+IF($J68="Y",$C$10,0)),0))) -> 30 | M68: H2FS | N68: 0 | O68: =WORKDAY($P$67,1+$N68,Holidays!$B$5:$B$60) -> 46491 | P68: =IF($K68="N",WORKDAY($O68,-1,Holidays!$B$5:$B$60),IF($L68=0,$O68,WORKDAY($O68,$L68-1,Holidays!$B$5:$B$60))) -> 46533 | Q68: Not started | R68: =IF(AND($G68="HOLD",$K68="Y"),"■ HOLD: go/no-go. ","") | S68: Duration set in C12.
A69: H4 | B69: H Sale & close-out | C69: Memorandum of sale; buyer's mortgage valuation | D69: Agent / buyer | E69: Both | H69: 10 | I69: 10 | J69: N | K69: =IF(AND(OR($E69="Both",$E69=$C$6),OR($F69="",IFERROR(INDEX($F$5:$F$13,MATCH($F69,$E$5:$E$13,0)),"Y")="Y")),"Y","N") -> Y | L69: =IF($K69="N",0,IF(IF($C$6="Auction",$H69,$I69)=0,0,ROUNDUP(IF($C$6="Auction",$H69,$I69)*(1+IF($J69="Y",$C$10,0)),0))) -> 10 | M69: H3FS | N69: 0 | O69: =WORKDAY($P$68,1+$N69,Holidays!$B$5:$B$60) -> 46534 | P69: =IF($K69="N",WORKDAY($O69,-1,Holidays!$B$5:$B$60),IF($L69=0,$O69,WORKDAY($O69,$L69-1,Holidays!$B$5:$B$60))) -> 46548 | Q69: Not started | R69: =IF(AND($G69="HOLD",$K69="Y"),"■ HOLD: go/no-go. ","")
A70: H5 | B70: H Sale & close-out | C70: Buyer's searches, enquiries and survey; supply certificates | D70: Solicitors | E70: Both | H70: 40 | I70: 40 | J70: N | K70: =IF(AND(OR($E70="Both",$E70=$C$6),OR($F70="",IFERROR(INDEX($F$5:$F$13,MATCH($F70,$E$5:$E$13,0)),"Y")="Y")),"Y","N") -> Y | L70: =IF($K70="N",0,IF(IF($C$6="Auction",$H70,$I70)=0,0,ROUNDUP(IF($C$6="Auction",$H70,$I70)*(1+IF($J70="Y",$C$10,0)),0))) -> 40 | M70: H3FS | N70: 0 | O70: =WORKDAY($P$68,1+$N70,Holidays!$B$5:$B$60) -> 46534 | P70: =IF($K70="N",WORKDAY($O70,-1,Holidays!$B$5:$B$60),IF($L70=0,$O70,WORKDAY($O70,$L70-1,Holidays!$B$5:$B$60))) -> 46590 | Q70: Not started | R70: =IF(AND($G70="HOLD",$K70="Y"),"■ HOLD: go/no-go. ","") | S70: Chase weekly. Typical sale-agreed → completion: 12–16 weeks.
A71: H6 | B71: H Sale & close-out | C71: Exchange contracts on sale | D71: Solicitors | E71: Both | H71: 0 | I71: 0 | J71: N | K71: =IF(AND(OR($E71="Both",$E71=$C$6),OR($F71="",IFERROR(INDEX($F$5:$F$13,MATCH($F71,$E$5:$E$13,0)),"Y")="Y")),"Y","N") -> Y | L71: =IF($K71="N",0,IF(IF($C$6="Auction",$H71,$I71)=0,0,ROUNDUP(IF($C$6="Auction",$H71,$I71)*(1+IF($J71="Y",$C$10,0)),0))) -> 0 | M71: H4FS; H5FS; G1FS | N71: 0 | O71: =MAX(WORKDAY($P$69,1+$N71,Holidays!$B$5:$B$60),WORKDAY($P$70,1+$N71,Holidays!$B$5:$B$60),WORKDAY($P$61,1+$N71,Holidays!$B$5:$B$60)) -> 46591 | P71: =IF($K71="N",WORKDAY($O71,-1,Holidays!$B$5:$B$60),IF($L71=0,$O71,WORKDAY($O71,$L71-1,Holidays!$B$5:$B$60))) -> 46591 | Q71: Not started | R71: =IF(AND($G71="HOLD",$K71="Y"),"■ HOLD: go/no-go. ","")
A72: H7 | B72: H Sale & close-out | C72: SALE COMPLETION: bridge redeemed | D72: Solicitor | E72: Both | H72: 0 | I72: 0 | J72: N | K72: =IF(AND(OR($E72="Both",$E72=$C$6),OR($F72="",IFERROR(INDEX($F$5:$F$13,MATCH($F72,$E$5:$E$13,0)),"Y")="Y")),"Y","N") -> Y | L72: =IF($K72="N",0,IF(IF($C$6="Auction",$H72,$I72)=0,0,ROUNDUP(IF($C$6="Auction",$H72,$I72)*(1+IF($J72="Y",$C$10,0)),0))) -> 0 | M72: H6FS | N72: =$C$15-1 -> 9 | O72: =WORKDAY($P$71,1+$N72,Holidays!$B$5:$B$60) -> 46605 | P72: =IF($K72="N",WORKDAY($O72,-1,Holidays!$B$5:$B$60),IF($L72=0,$O72,WORKDAY($O72,$L72-1,Holidays!$B$5:$B$60))) -> 46605 | Q72: Not started | R72: =IF(AND($G72="HOLD",$K72="Y"),"■ HOLD: go/no-go. ","")&IF(($P72-$P$32)/30.44>$C$13,"⚠ Sale completes after bridge term: extension cost. ","") | S72: Lag = C15 − 1 so completion lands C15 working days after exchange.
A73: H8 | B73: H Sale & close-out | C73: Retention released (end of defects period) | D73: Paul | E73: Both | H73: 0 | I73: 0 | J73: N | K73: =IF(AND(OR($E73="Both",$E73=$C$6),OR($F73="",IFERROR(INDEX($F$5:$F$13,MATCH($F73,$E$5:$E$13,0)),"Y")="Y")),"Y","N") -> Y | L73: =IF($K73="N",0,IF(IF($C$6="Auction",$H73,$I73)=0,0,ROUNDUP(IF($C$6="Auction",$H73,$I73)*(1+IF($J73="Y",$C$10,0)),0))) -> 0 | M73: G3FS | N73: 60 | O73: =WORKDAY($P$63,1+$N73,Holidays!$B$5:$B$60) -> 46574 | P73: =IF($K73="N",WORKDAY($O73,-1,Holidays!$B$5:$B$60),IF($L73=0,$O73,WORKDAY($O73,$L73-1,Holidays!$B$5:$B$60))) -> 46574 | Q73: Not started | R73: =IF(AND($G73="HOLD",$K73="Y"),"■ HOLD: go/no-go. ","") | S73: Lag 60 WD ≈ 3 months after practical completion.
A74: H9 | B74: H Sale & close-out | C74: Close-out: final P&L vs appraisal in DealsDash; lessons learned | D74: Paul | E74: Both | H74: 2 | I74: 2 | J74: N | K74: =IF(AND(OR($E74="Both",$E74=$C$6),OR($F74="",IFERROR(INDEX($F$5:$F$13,MATCH($F74,$E$5:$E$13,0)),"Y")="Y")),"Y","N") -> Y | L74: =IF($K74="N",0,IF(IF($C$6="Auction",$H74,$I74)=0,0,ROUNDUP(IF($C$6="Auction",$H74,$I74)*(1+IF($J74="Y",$C$10,0)),0))) -> 2 | M74: H7FS | N74: 0 | O74: =WORKDAY($P$72,1+$N74,Holidays!$B$5:$B$60) -> 46608 | P74: =IF($K74="N",WORKDAY($O74,-1,Holidays!$B$5:$B$60),IF($L74=0,$O74,WORKDAY($O74,$L74-1,Holidays!$B$5:$B$60))) -> 46609 | Q74: Not started | R74: =IF(AND($G74="HOLD",$K74="Y"),"■ HOLD: go/no-go. ","") | S74: Feed actual durations back into this template.

Sheet Deal 2
A1: VIXIV LTD — Flip programme: Deal 2
A2: Edit only the YELLOW cells (blue text). Dates, Gantt and flags recalculate. Durations are working days. Example values shown — replace with your deal.
B4: DEAL INPUTS | E4: SCOPE SWITCHES (Y/N) | H4: KEY DATES (calculated)
B5: Deal name / address | C5: EXAMPLE — 3-bed semi via agent (replace) | E5: Pre-2000 build | F5: Y | H5: Purchase completion | I5: =$P$32 -> 46477
B6: Purchase route | C6: Estate agent | E6: Structural | F6: N | H6: Works start (strip-out) | I6: =$O$40 -> 46485
B7: Deal secured date | C7: 46419 | E7: Damp/timber | F7: Y | H7: Practical completion | I7: =$O$63 -> 46563
B8: Auction completion period (calendar days) | C8: 28 | E8: Roof/external | F8: N | H8: Listed | I8: =$O$67 -> 46568
B9: Agent route: exchange → completion (WD) | C9: 10 | E9: Windows/doors | F9: Y | H9: Sale agreed | I9: =$P$68 -> 46610
B10: Contingency on construction durations | C10: 0.15 | E10: Rewire | F10: Y | H10: Sale completed | I10: =$P$72 -> 46682
B11: Winter drying allowance (extra WD, Nov–Feb) | C11: 3 | E11: Heating/boiler | F11: Y | H11: Build duration (WD) | I11: =NETWORKDAYS($I$6,$I$7,Holidays!$B$5:$B$60) -> 55
B12: WD to agree a sale after listing | C12: 30 | E12: Kitchen | F12: Y | H12: Months owned (completion → sale) | I12: =($I$10-$I$5)/30.44 -> 6.7345598
B13: Bridge term (months) | C13: 12 | E13: Bathroom | F13: Y | H13: Bridge headroom (months) | I13: =$C$13-$I$12 -> 5.2654402
B14: Lead contractor | C14: Friend (general builder) | H14: Deal secured → sale completed (days) | I14: =$I$10-$C$7 -> 263
B15: Sale: exchange → completion (WD) | C15: 10
B17: Gantt key: | C17: A Purchase & DD | D17: B Pre-start | E17: C Strip-out & structure | F17: D First fix | G17: E Plaster | H17: F Second fix & finish | I17: G Sign-off | J17: H Sale & close-out | K17: ■ milestone
U19: =TEXT(U20,"mmm yy") -> Feb 27 | V19: =IF(MONTH(V20)<>MONTH(U20),TEXT(V20,"mmm yy"),"") | W19: =IF(MONTH(W20)<>MONTH(V20),TEXT(W20,"mmm yy"),"") | X19: =IF(MONTH(X20)<>MONTH(W20),TEXT(X20,"mmm yy"),"") | Y19: =IF(MONTH(Y20)<>MONTH(X20),TEXT(Y20,"mmm yy"),"") -> Mar 27 | Z19: =IF(MONTH(Z20)<>MONTH(Y20),TEXT(Z20,"mmm yy"),"") | AA19: =IF(MONTH(AA20)<>MONTH(Z20),TEXT(AA20,"mmm yy"),"") | AB19: =IF(MONTH(AB20)<>MONTH(AA20),TEXT(AB20,"mmm yy"),"") | AC19: =IF(MONTH(AC20)<>MONTH(AB20),TEXT(AC20,"mmm yy"),"") | ... CB19: =IF(MONTH(CB20)<>MONTH(CA20),TEXT(CB20,"mmm yy"),"")
A20: ID | B20: Phase | C20: Activity | D20: Owner | E20: Route | F20: Scope switch | G20: Hold point | H20: Dur WD (auction) | I20: Dur WD (agent) | J20: Contingency? | K20: Applies? | L20: Dur used (WD) | M20: Predecessors | N20: Lag (WD) | O20: Start | P20: Finish | Q20: Status | R20: Flags | S20: Notes / what good looks like | U20: =$O$21-WEEKDAY($O$21,3) -> 46419 | V20: =U20+7 -> 46426 | W20: =V20+7 -> 46433 | X20: =W20+7 -> 46440 | Y20: =X20+7 -> 46447 | Z20: =Y20+7 -> 46454 | AA20: =Z20+7 -> 46461 | AB20: =AA20+7 -> 46468 | AC20: =AB20+7 -> 46475 | ... CB20: =CA20+7 -> 46832
A21: A1 | B21: A Purchase & DD | C21: Deal secured (auction: hammer falls = exchange; agent: offer accepted) | D21: Paul | E21: Both | H21: 0 | I21: 0 | J21: N | K21: =IF(AND(OR($E21="Both",$E21=$C$6),OR($F21="",IFERROR(INDEX($F$5:$F$13,MATCH($F21,$E$5:$E$13,0)),"Y")="Y")),"Y","N") -> Y | L21: =IF($K21="N",0,IF(IF($C$6="Auction",$H21,$I21)=0,0,ROUNDUP(IF($C$6="Auction",$H21,$I21)*(1+IF($J21="Y",$C$10,0)),0))) -> 0 | M21: — | N21: 0 | O21: =WORKDAY($C$7-1,1,Holidays!$B$5:$B$60) -> 46419 | P21: =IF($K21="N",WORKDAY($O21,-1,Holidays!$B$5:$B$60),IF($L21=0,$O21,WORKDAY($O21,$L21-1,Holidays!$B$5:$B$60))) -> 46419 | Q21: Not started | R21: =IF(AND($G21="HOLD",$K21="Y"),"■ HOLD: go/no-go. ","") | S21: Day 0. Everything else is driven from the date in C7.
A22: A2 | B22: A Purchase & DD | C22: Buildings insurance (unoccupied cover) in force | D22: Paul / broker | E22: Both | H22: 1 | I22: 1 | J22: N | K22: =IF(AND(OR($E22="Both",$E22=$C$6),OR($F22="",IFERROR(INDEX($F$5:$F$13,MATCH($F22,$E$5:$E$13,0)),"Y")="Y")),"Y","N") -> Y | L22: =IF($K22="N",0,IF(IF($C$6="Auction",$H22,$I22)=0,0,ROUNDUP(IF($C$6="Auction",$H22,$I22)*(1+IF($J22="Y",$C$10,0)),0))) -> 1 | M22: A1SS | N22: 0 | O22: =WORKDAY($O$21,$N22,Holidays!$B$5:$B$60) -> 46419 | P22: =IF($K22="N",WORKDAY($O22,-1,Holidays!$B$5:$B$60),IF($L22=0,$O22,WORKDAY($O22,$L22-1,Holidays!$B$5:$B$60))) -> 46419 | Q22: Not started | R22: =IF(AND($G22="HOLD",$K22="Y"),"■ HOLD: go/no-go. ","") | S22: Auction: risk passes to you at the hammer. Agent route: must be on cover from exchange at the latest.
A23: A3 | B23: A Purchase & DD | C23: Pay 10% deposit + buyer's premium / auction fees | D23: Paul | E23: Auction | H23: 1 | I23: 0 | J23: N | K23: =IF(AND(OR($E23="Both",$E23=$C$6),OR($F23="",IFERROR(INDEX($F$5:$F$13,MATCH($F23,$E$5:$E$13,0)),"Y")="Y")),"Y","N") -> N | L23: =IF($K23="N",0,IF(IF($C$6="Auction",$H23,$I23)=0,0,ROUNDUP(IF($C$6="Auction",$H23,$I23)*(1+IF($J23="Y",$C$10,0)),0))) -> 0 | M23: A1SS | N23: 0 | O23: =WORKDAY($O$21,$N23,Holidays!$B$5:$B$60) -> 46419 | P23: =IF($K23="N",WORKDAY($O23,-1,Holidays!$B$5:$B$60),IF($L23=0,$O23,WORKDAY($O23,$L23-1,Holidays!$B$5:$B$60))) -> 46416 | Q23: Not started | R23: =IF(AND($G23="HOLD",$K23="Y"),"■ HOLD: go/no-go. ","") | S23: Paid on the day. Funds must be ready before you bid.
A24: A4 | B24: A Purchase & DD | C24: Instruct solicitor; legal pack / memorandum of sale to solicitor and lender | D24: Paul | E24: Both | H24: 2 | I24: 2 | J24: N | K24: =IF(AND(OR($E24="Both",$E24=$C$6),OR($F24="",IFERROR(INDEX($F$5:$F$13,MATCH($F24,$E$5:$E$13,0)),"Y")="Y")),"Y","N") -> Y | L24: =IF($K24="N",0,IF(IF($C$6="Auction",$H24,$I24)=0,0,ROUNDUP(IF($C$6="Auction",$H24,$I24)*(1+IF($J24="Y",$C$10,0)),0))) -> 2 | M24: A1SS | N24: 0 | O24: =WORKDAY($O$21,$N24,Holidays!$B$5:$B$60) -> 46419 | P24: =IF($K24="N",WORKDAY($O24,-1,Holidays!$B$5:$B$60),IF($L24=0,$O24,WORKDAY($O24,$L24-1,Holidays!$B$5:$B$60))) -> 46420 | Q24: Not started | R24: =IF(AND($G24="HOLD",$K24="Y"),"■ HOLD: go/no-go. ","")
A25: A5 | B25: A Purchase & DD | C25: Bridging valuation instructed and inspection done | D25: Broker / lender | E25: Both | H25: 5 | I25: 5 | J25: N | K25: =IF(AND(OR($E25="Both",$E25=$C$6),OR($F25="",IFERROR(INDEX($F$5:$F$13,MATCH($F25,$E$5:$E$13,0)),"Y")="Y")),"Y","N") -> Y | L25: =IF($K25="N",0,IF(IF($C$6="Auction",$H25,$I25)=0,0,ROUNDUP(IF($C$6="Auction",$H25,$I25)*(1+IF($J25="Y",$C$10,0)),0))) -> 5 | M25: A4SS | N25: 1 | O25: =WORKDAY($O$24,$N25,Holidays!$B$5:$B$60) -> 46420 | P25: =IF($K25="N",WORKDAY($O25,-1,Holidays!$B$5:$B$60),IF($L25=0,$O25,WORKDAY($O25,$L25-1,Holidays!$B$5:$B$60))) -> 46426 | Q25: Not started | R25: =IF(AND($G25="HOLD",$K25="Y"),"■ HOLD: go/no-go. ","") | S25: Ideally have a decision in principle BEFORE the auction.
A26: A6 | B26: A Purchase & DD | C26: Bridging underwriting and formal loan offer | D26: Lender | E26: Both | H26: 5 | I26: 5 | J26: N | K26: =IF(AND(OR($E26="Both",$E26=$C$6),OR($F26="",IFERROR(INDEX($F$5:$F$13,MATCH($F26,$E$5:$E$13,0)),"Y")="Y")),"Y","N") -> Y | L26: =IF($K26="N",0,IF(IF($C$6="Auction",$H26,$I26)=0,0,ROUNDUP(IF($C$6="Auction",$H26,$I26)*(1+IF($J26="Y",$C$10,0)),0))) -> 5 | M26: A5FS | N26: 0 | O26: =WORKDAY($P$25,1+$N26,Holidays!$B$5:$B$60) -> 46427 | P26: =IF($K26="N",WORKDAY($O26,-1,Holidays!$B$5:$B$60),IF($L26=0,$O26,WORKDAY($O26,$L26-1,Holidays!$B$5:$B$60))) -> 46433 | Q26: Not started | R26: =IF(AND($G26="HOLD",$K26="Y"),"■ HOLD: go/no-go. ","")
A27: A7 | B27: A Purchase & DD | C27: Searches and enquiries raised and answered | D27: Solicitor | E27: Estate agent | H27: 0 | I27: 25 | J27: N | K27: =IF(AND(OR($E27="Both",$E27=$C$6),OR($F27="",IFERROR(INDEX($F$5:$F$13,MATCH($F27,$E$5:$E$13,0)),"Y")="Y")),"Y","N") -> Y | L27: =IF($K27="N",0,IF(IF($C$6="Auction",$H27,$I27)=0,0,ROUNDUP(IF($C$6="Auction",$H27,$I27)*(1+IF($J27="Y",$C$10,0)),0))) -> 25 | M27: A4FS | N27: 0 | O27: =WORKDAY($P$24,1+$N27,Holidays!$B$5:$B$60) -> 46421 | P27: =IF($K27="N",WORKDAY($O27,-1,Holidays!$B$5:$B$60),IF($L27=0,$O27,WORKDAY($O27,$L27-1,Holidays!$B$5:$B$60))) -> 46455 | Q27: Not started | R27: =IF(AND($G27="HOLD",$K27="Y"),"■ HOLD: go/no-go. ","") | S27: Auction route: done BEFORE bidding (see DD Checklist).
A28: A8 | B28: A Purchase & DD | C28: Independent survey + builder walk-round for quote | D28: Surveyor / builder | E28: Estate agent | H28: 0 | I28: 10 | J28: N | K28: =IF(AND(OR($E28="Both",$E28=$C$6),OR($F28="",IFERROR(INDEX($F$5:$F$13,MATCH($F28,$E$5:$E$13,0)),"Y")="Y")),"Y","N") -> Y | L28: =IF($K28="N",0,IF(IF($C$6="Auction",$H28,$I28)=0,0,ROUNDUP(IF($C$6="Auction",$H28,$I28)*(1+IF($J28="Y",$C$10,0)),0))) -> 10 | M28: A4SS | N28: 2 | O28: =WORKDAY($O$24,$N28,Holidays!$B$5:$B$60) -> 46421 | P28: =IF($K28="N",WORKDAY($O28,-1,Holidays!$B$5:$B$60),IF($L28=0,$O28,WORKDAY($O28,$L28-1,Holidays!$B$5:$B$60))) -> 46434 | Q28: Not started | R28: =IF(AND($G28="HOLD",$K28="Y"),"■ HOLD: go/no-go. ","")
A29: A9 | B29: A Purchase & DD | C29: Review title, searches and survey: renegotiate or withdraw | D29: Paul + mentor | E29: Estate agent | G29: HOLD | H29: 0 | I29: 3 | J29: N | K29: =IF(AND(OR($E29="Both",$E29=$C$6),OR($F29="",IFERROR(INDEX($F$5:$F$13,MATCH($F29,$E$5:$E$13,0)),"Y")="Y")),"Y","N") -> Y | L29: =IF($K29="N",0,IF(IF($C$6="Auction",$H29,$I29)=0,0,ROUNDUP(IF($C$6="Auction",$H29,$I29)*(1+IF($J29="Y",$C$10,0)),0))) -> 3 | M29: A7FS; A8FS | N29: 0 | O29: =MAX(WORKDAY($P$27,1+$N29,Holidays!$B$5:$B$60),WORKDAY($P$28,1+$N29,Holidays!$B$5:$B$60)) -> 46456 | P29: =IF($K29="N",WORKDAY($O29,-1,Holidays!$B$5:$B$60),IF($L29=0,$O29,WORKDAY($O29,$L29-1,Holidays!$B$5:$B$60))) -> 46458 | Q29: Not started | R29: =IF(AND($G29="HOLD",$K29="Y"),"■ HOLD: go/no-go. ","") -> ■ HOLD: go/no-go. | S29: Re-run the DealsDash appraisal with real costs. Walk away if it fails.
A30: A10 | B30: A Purchase & DD | C30: Exchange contracts (deposit paid) | D30: Solicitor | E30: Estate agent | H30: 0 | I30: 0 | J30: N | K30: =IF(AND(OR($E30="Both",$E30=$C$6),OR($F30="",IFERROR(INDEX($F$5:$F$13,MATCH($F30,$E$5:$E$13,0)),"Y")="Y")),"Y","N") -> Y | L30: =IF($K30="N",0,IF(IF($C$6="Auction",$H30,$I30)=0,0,ROUNDUP(IF($C$6="Auction",$H30,$I30)*(1+IF($J30="Y",$C$10,0)),0))) -> 0 | M30: A9FS; A6FS | N30: 0 | O30: =MAX(WORKDAY($P$29,1+$N30,Holidays!$B$5:$B$60),WORKDAY($P$26,1+$N30,Holidays!$B$5:$B$60)) -> 46461 | P30: =IF($K30="N",WORKDAY($O30,-1,Holidays!$B$5:$B$60),IF($L30=0,$O30,WORKDAY($O30,$L30-1,Holidays!$B$5:$B$60))) -> 46461 | Q30: Not started | R30: =IF(AND($G30="HOLD",$K30="Y"),"■ HOLD: go/no-go. ","") | S30: Legally committed from here.
A31: A11 | B31: A Purchase & DD | C31: Lender's legal work, report on title, funds requested | D31: Solicitors | E31: Both | H31: 5 | I31: 5 | J31: N | K31: =IF(AND(OR($E31="Both",$E31=$C$6),OR($F31="",IFERROR(INDEX($F$5:$F$13,MATCH($F31,$E$5:$E$13,0)),"Y")="Y")),"Y","N") -> Y | L31: =IF($K31="N",0,IF(IF($C$6="Auction",$H31,$I31)=0,0,ROUNDUP(IF($C$6="Auction",$H31,$I31)*(1+IF($J31="Y",$C$10,0)),0))) -> 5 | M31: A6FS; A10FS | N31: 0 | O31: =MAX(WORKDAY($P$26,1+$N31,Holidays!$B$5:$B$60),WORKDAY($P$30,1+$N31,Holidays!$B$5:$B$60)) -> 46462 | P31: =IF($K31="N",WORKDAY($O31,-1,Holidays!$B$5:$B$60),IF($L31=0,$O31,WORKDAY($O31,$L31-1,Holidays!$B$5:$B$60))) -> 46468 | Q31: Not started | R31: =IF(AND($G31="HOLD",$K31="Y"),"■ HOLD: go/no-go. ","")
A32: A12 | B32: A Purchase & DD | C32: PURCHASE COMPLETION: keys released | D32: Solicitor | E32: Both | H32: 0 | I32: 0 | J32: N | K32: =IF(AND(OR($E32="Both",$E32=$C$6),OR($F32="",IFERROR(INDEX($F$5:$F$13,MATCH($F32,$E$5:$E$13,0)),"Y")="Y")),"Y","N") -> Y | L32: =IF($K32="N",0,IF(IF($C$6="Auction",$H32,$I32)=0,0,ROUNDUP(IF($C$6="Auction",$H32,$I32)*(1+IF($J32="Y",$C$10,0)),0))) -> 0 | M32: A1 (auction) / A10, A11 (agent) | N32: 0 | O32: =IF($C$6="Auction",WORKDAY($O$21+$C$8-1,1,Holidays!$B$5:$B$60),MAX(WORKDAY($P$30,$C$9,Holidays!$B$5:$B$60),WORKDAY($P$31,1,Holidays!$B$5:$B$60))) -> 46477 | P32: =IF($K32="N",WORKDAY($O32,-1,Holidays!$B$5:$B$60),IF($L32=0,$O32,WORKDAY($O32,$L32-1,Holidays!$B$5:$B$60))) -> 46477 | Q32: Not started | R32: =IF(AND($G32="HOLD",$K32="Y"),"■ HOLD: go/no-go. ","")&IF(AND($C$6="Auction",$P$31>$O32),"⚠ Finance not ready by auction completion: deposit at risk. ","") | S32: Auction: fixed by contract (usually 28 calendar days). Agent: exchange + C9 working days.
A33: B1 | B33: B Pre-start | C33: Builder schedule of works and measured scope | D33: Builder | E33: Both | H33: 3 | I33: 3 | J33: N | K33: =IF(AND(OR($E33="Both",$E33=$C$6),OR($F33="",IFERROR(INDEX($F$5:$F$13,MATCH($F33,$E$5:$E$13,0)),"Y")="Y")),"Y","N") -> Y | L33: =IF($K33="N",0,IF(IF($C$6="Auction",$H33,$I33)=0,0,ROUNDUP(IF($C$6="Auction",$H33,$I33)*(1+IF($J33="Y",$C$10,0)),0))) -> 3 | M33: A1FS; A8FS | N33: 0 | O33: =MAX(WORKDAY($P$21,1+$N33,Holidays!$B$5:$B$60),WORKDAY($P$28,1+$N33,Holidays!$B$5:$B$60)) -> 46435 | P33: =IF($K33="N",WORKDAY($O33,-1,Holidays!$B$5:$B$60),IF($L33=0,$O33,WORKDAY($O33,$L33-1,Holidays!$B$5:$B$60))) -> 46437 | Q33: Not started | R33: =IF(AND($G33="HOLD",$K33="Y"),"■ HOLD: go/no-go. ","") | S33: Auction: arrange access via auctioneer/seller, or use the pre-bid viewing scope.
A34: B2 | B34: B Pre-start | C34: Fixed-price quote(s) received; mentor review | D34: Builder / mentor | E34: Both | H34: 5 | I34: 5 | J34: N | K34: =IF(AND(OR($E34="Both",$E34=$C$6),OR($F34="",IFERROR(INDEX($F$5:$F$13,MATCH($F34,$E$5:$E$13,0)),"Y")="Y")),"Y","N") -> Y | L34: =IF($K34="N",0,IF(IF($C$6="Auction",$H34,$I34)=0,0,ROUNDUP(IF($C$6="Auction",$H34,$I34)*(1+IF($J34="Y",$C$10,0)),0))) -> 5 | M34: B1FS | N34: 0 | O34: =WORKDAY($P$33,1+$N34,Holidays!$B$5:$B$60) -> 46440 | P34: =IF($K34="N",WORKDAY($O34,-1,Holidays!$B$5:$B$60),IF($L34=0,$O34,WORKDAY($O34,$L34-1,Holidays!$B$5:$B$60))) -> 46444 | Q34: Not started | R34: =IF(AND($G34="HOLD",$K34="Y"),"■ HOLD: go/no-go. ","")
A35: B3 | B35: B Pre-start | C35: Sign contract: scope, stage payments, 5% retention; check insurance, verify CIS | D35: Paul | E35: Both | G35: HOLD | H35: 2 | I35: 2 | J35: N | K35: =IF(AND(OR($E35="Both",$E35=$C$6),OR($F35="",IFERROR(INDEX($F$5:$F$13,MATCH($F35,$E$5:$E$13,0)),"Y")="Y")),"Y","N") -> Y | L35: =IF($K35="N",0,IF(IF($C$6="Auction",$H35,$I35)=0,0,ROUNDUP(IF($C$6="Auction",$H35,$I35)*(1+IF($J35="Y",$C$10,0)),0))) -> 2 | M35: B2FS | N35: 0 | O35: =WORKDAY($P$34,1+$N35,Holidays!$B$5:$B$60) -> 46447 | P35: =IF($K35="N",WORKDAY($O35,-1,Holidays!$B$5:$B$60),IF($L35=0,$O35,WORKDAY($O35,$L35-1,Holidays!$B$5:$B$60))) -> 46448 | Q35: Not started | R35: =IF(AND($G35="HOLD",$K35="Y"),"■ HOLD: go/no-go. ","") -> ■ HOLD: go/no-go. | S35: No signed scope + price = no start.
A36: B4 | B36: B Pre-start | C36: Order long-lead items (kitchen, boiler, windows) | D36: Paul / builder | E36: Both | H36: 1 | I36: 1 | J36: N | K36: =IF(AND(OR($E36="Both",$E36=$C$6),OR($F36="",IFERROR(INDEX($F$5:$F$13,MATCH($F36,$E$5:$E$13,0)),"Y")="Y")),"Y","N") -> Y | L36: =IF($K36="N",0,IF(IF($C$6="Auction",$H36,$I36)=0,0,ROUNDUP(IF($C$6="Auction",$H36,$I36)*(1+IF($J36="Y",$C$10,0)),0))) -> 1 | M36: B3FS | N36: 0 | O36: =WORKDAY($P$35,1+$N36,Holidays!$B$5:$B$60) -> 46449 | P36: =IF($K36="N",WORKDAY($O36,-1,Holidays!$B$5:$B$60),IF($L36=0,$O36,WORKDAY($O36,$L36-1,Holidays!$B$5:$B$60))) -> 46449 | Q36: Not started | R36: =IF(AND($G36="HOLD",$K36="Y"),"■ HOLD: go/no-go. ","")
A37: B5 | B37: B Pre-start | C37: Long-lead delivery window | D37: Suppliers | E37: Both | H37: 15 | I37: 15 | J37: N | K37: =IF(AND(OR($E37="Both",$E37=$C$6),OR($F37="",IFERROR(INDEX($F$5:$F$13,MATCH($F37,$E$5:$E$13,0)),"Y")="Y")),"Y","N") -> Y | L37: =IF($K37="N",0,IF(IF($C$6="Auction",$H37,$I37)=0,0,ROUNDUP(IF($C$6="Auction",$H37,$I37)*(1+IF($J37="Y",$C$10,0)),0))) -> 15 | M37: B4FS | N37: 0 | O37: =WORKDAY($P$36,1+$N37,Holidays!$B$5:$B$60) -> 46450 | P37: =IF($K37="N",WORKDAY($O37,-1,Holidays!$B$5:$B$60),IF($L37=0,$O37,WORKDAY($O37,$L37-1,Holidays!$B$5:$B$60))) -> 46470 | Q37: Not started | R37: =IF(AND($G37="HOLD",$K37="Y"),"■ HOLD: go/no-go. ","") | S37: Typical 3 weeks; windows can be 4–6. Edit to supplier quote.
A38: B6 | B38: B Pre-start | C38: Asbestos refurbishment survey | D38: Surveyor | E38: Both | F38: Pre-2000 build | H38: 5 | I38: 5 | J38: N | K38: =IF(AND(OR($E38="Both",$E38=$C$6),OR($F38="",IFERROR(INDEX($F$5:$F$13,MATCH($F38,$E$5:$E$13,0)),"Y")="Y")),"Y","N") -> Y | L38: =IF($K38="N",0,IF(IF($C$6="Auction",$H38,$I38)=0,0,ROUNDUP(IF($C$6="Auction",$H38,$I38)*(1+IF($J38="Y",$C$10,0)),0))) -> 5 | M38: A12FS | N38: 0 | O38: =WORKDAY($P$32,1+$N38,Holidays!$B$5:$B$60) -> 46478 | P38: =IF($K38="N",WORKDAY($O38,-1,Holidays!$B$5:$B$60),IF($L38=0,$O38,WORKDAY($O38,$L38-1,Holidays!$B$5:$B$60))) -> 46484 | Q38: Not started | R38: =IF(AND($G38="HOLD",$K38="Y"),"■ HOLD: go/no-go. ","") | S38: Before any intrusive work on a pre-2000 property (HSE guidance — confirm with contractor).
A39: B7 | B39: B Pre-start | C39: Utilities and meter readings, council tax, change locks, skip, start photos | D39: Paul | E39: Both | H39: 1 | I39: 1 | J39: N | K39: =IF(AND(OR($E39="Both",$E39=$C$6),OR($F39="",IFERROR(INDEX($F$5:$F$13,MATCH($F39,$E$5:$E$13,0)),"Y")="Y")),"Y","N") -> Y | L39: =IF($K39="N",0,IF(IF($C$6="Auction",$H39,$I39)=0,0,ROUNDUP(IF($C$6="Auction",$H39,$I39)*(1+IF($J39="Y",$C$10,0)),0))) -> 1 | M39: A12FS | N39: 0 | O39: =WORKDAY($P$32,1+$N39,Holidays!$B$5:$B$60) -> 46478 | P39: =IF($K39="N",WORKDAY($O39,-1,Holidays!$B$5:$B$60),IF($L39=0,$O39,WORKDAY($O39,$L39-1,Holidays!$B$5:$B$60))) -> 46478 | Q39: Not started | R39: =IF(AND($G39="HOLD",$K39="Y"),"■ HOLD: go/no-go. ","")
A40: C1 | B40: C Strip-out & structure | C40: Strip-out: kitchen, bathroom, flooring, blown plaster | D40: Builder | E40: Both | H40: 4 | I40: 4 | J40: Y | K40: =IF(AND(OR($E40="Both",$E40=$C$6),OR($F40="",IFERROR(INDEX($F$5:$F$13,MATCH($F40,$E$5:$E$13,0)),"Y")="Y")),"Y","N") -> Y | L40: =IF($K40="N",0,IF(IF($C$6="Auction",$H40,$I40)=0,0,ROUNDUP(IF($C$6="Auction",$H40,$I40)*(1+IF($J40="Y",$C$10,0)),0))) -> 5 | M40: B7FS; B6FS; B3FS | N40: 0 | O40: =MAX(WORKDAY($P$39,1+$N40,Holidays!$B$5:$B$60),WORKDAY($P$38,1+$N40,Holidays!$B$5:$B$60),WORKDAY($P$35,1+$N40,Holidays!$B$5:$B$60)) -> 46485 | P40: =IF($K40="N",WORKDAY($O40,-1,Holidays!$B$5:$B$60),IF($L40=0,$O40,WORKDAY($O40,$L40-1,Holidays!$B$5:$B$60))) -> 46491 | Q40: Not started | R40: =IF(AND($G40="HOLD",$K40="Y"),"■ HOLD: go/no-go. ","")
A41: C2 | B41: C Strip-out & structure | C41: Opening-up inspection; update costs in DealsDash | D41: Paul + builder | E41: Both | G41: HOLD | H41: 1 | I41: 1 | J41: N | K41: =IF(AND(OR($E41="Both",$E41=$C$6),OR($F41="",IFERROR(INDEX($F$5:$F$13,MATCH($F41,$E$5:$E$13,0)),"Y")="Y")),"Y","N") -> Y | L41: =IF($K41="N",0,IF(IF($C$6="Auction",$H41,$I41)=0,0,ROUNDUP(IF($C$6="Auction",$H41,$I41)*(1+IF($J41="Y",$C$10,0)),0))) -> 1 | M41: C1FS | N41: 0 | O41: =WORKDAY($P$40,1+$N41,Holidays!$B$5:$B$60) -> 46492 | P41: =IF($K41="N",WORKDAY($O41,-1,Holidays!$B$5:$B$60),IF($L41=0,$O41,WORKDAY($O41,$L41-1,Holidays!$B$5:$B$60))) -> 46492 | Q41: Not started | R41: =IF(AND($G41="HOLD",$K41="Y"),"■ HOLD: go/no-go. ","") -> ■ HOLD: go/no-go. | S41: Hidden defects show here. Re-check profit vs target before committing more spend.
A42: C3 | B42: C Strip-out & structure | C42: Structural works (engineer design + Building Control notice) | D42: Builder / engineer | E42: Both | F42: Structural | H42: 5 | I42: 5 | J42: Y | K42: =IF(AND(OR($E42="Both",$E42=$C$6),OR($F42="",IFERROR(INDEX($F$5:$F$13,MATCH($F42,$E$5:$E$13,0)),"Y")="Y")),"Y","N") -> N | L42: =IF($K42="N",0,IF(IF($C$6="Auction",$H42,$I42)=0,0,ROUNDUP(IF($C$6="Auction",$H42,$I42)*(1+IF($J42="Y",$C$10,0)),0))) -> 0 | M42: C2FS | N42: 0 | O42: =WORKDAY($P$41,1+$N42,Holidays!$B$5:$B$60) -> 46493 | P42: =IF($K42="N",WORKDAY($O42,-1,Holidays!$B$5:$B$60),IF($L42=0,$O42,WORKDAY($O42,$L42-1,Holidays!$B$5:$B$60))) -> 46492 | Q42: Not started | R42: =IF(AND($G42="HOLD",$K42="Y"),"■ HOLD: go/no-go. ","")
A43: C4 | B43: C Strip-out & structure | C43: Damp-proofing / timber treatment | D43: Specialist | E43: Both | F43: Damp/timber | H43: 3 | I43: 3 | J43: Y | K43: =IF(AND(OR($E43="Both",$E43=$C$6),OR($F43="",IFERROR(INDEX($F$5:$F$13,MATCH($F43,$E$5:$E$13,0)),"Y")="Y")),"Y","N") -> Y | L43: =IF($K43="N",0,IF(IF($C$6="Auction",$H43,$I43)=0,0,ROUNDUP(IF($C$6="Auction",$H43,$I43)*(1+IF($J43="Y",$C$10,0)),0))) -> 4 | M43: C2FS | N43: 0 | O43: =WORKDAY($P$41,1+$N43,Holidays!$B$5:$B$60) -> 46493 | P43: =IF($K43="N",WORKDAY($O43,-1,Holidays!$B$5:$B$60),IF($L43=0,$O43,WORKDAY($O43,$L43-1,Holidays!$B$5:$B$60))) -> 46498 | Q43: Not started | R43: =IF(AND($G43="HOLD",$K43="Y"),"■ HOLD: go/no-go. ","") | S43: Get the guarantee for the sale pack.
A44: C5 | B44: C Strip-out & structure | C44: Roof and external repairs (roof, gutters, pointing, render) | D44: Roofer / builder | E44: Both | F44: Roof/external | H44: 8 | I44: 8 | J44: Y | K44: =IF(AND(OR($E44="Both",$E44=$C$6),OR($F44="",IFERROR(INDEX($F$5:$F$13,MATCH($F44,$E$5:$E$13,0)),"Y")="Y")),"Y","N") -> N | L44: =IF($K44="N",0,IF(IF($C$6="Auction",$H44,$I44)=0,0,ROUNDUP(IF($C$6="Auction",$H44,$I44)*(1+IF($J44="Y",$C$10,0)),0))) -> 0 | M44: C2FS | N44: 0 | O44: =WORKDAY($P$41,1+$N44,Holidays!$B$5:$B$60) -> 46493 | P44: =IF($K44="N",WORKDAY($O44,-1,Holidays!$B$5:$B$60),IF($L44=0,$O44,WORKDAY($O44,$L44-1,Holidays!$B$5:$B$60))) -> 46492 | Q44: Not started | R44: =IF(AND($G44="HOLD",$K44="Y"),"■ HOLD: go/no-go. ","")&IF(AND($K44="Y",OR(MONTH($O44)>=11,MONTH($O44)<=2)),"⚠ External work in Nov–Feb: weather risk. ","")
A45: C6 | B45: C Strip-out & structure | C45: Windows and external doors fitted | D45: Installer | E45: Both | F45: Windows/doors | H45: 3 | I45: 3 | J45: Y | K45: =IF(AND(OR($E45="Both",$E45=$C$6),OR($F45="",IFERROR(INDEX($F$5:$F$13,MATCH($F45,$E$5:$E$13,0)),"Y")="Y")),"Y","N") -> Y | L45: =IF($K45="N",0,IF(IF($C$6="Auction",$H45,$I45)=0,0,ROUNDUP(IF($C$6="Auction",$H45,$I45)*(1+IF($J45="Y",$C$10,0)),0))) -> 4 | M45: C2FS; B5FS | N45: 0 | O45: =MAX(WORKDAY($P$41,1+$N45,Holidays!$B$5:$B$60),WORKDAY($P$37,1+$N45,Holidays!$B$5:$B$60)) -> 46493 | P45: =IF($K45="N",WORKDAY($O45,-1,Holidays!$B$5:$B$60),IF($L45=0,$O45,WORKDAY($O45,$L45-1,Holidays!$B$5:$B$60))) -> 46498 | Q45: Not started | R45: =IF(AND($G45="HOLD",$K45="Y"),"■ HOLD: go/no-go. ","")&IF(AND($K45="Y",OR(MONTH($O45)>=11,MONTH($O45)<=2)),"⚠ External work in Nov–Feb: weather risk. ","") | S45: Keep FENSA certificate.
A46: D1 | B46: D First fix | C46: Electrical first fix (rewire) | D46: Electrician | E46: Both | F46: Rewire | H46: 4 | I46: 4 | J46: Y | K46: =IF(AND(OR($E46="Both",$E46=$C$6),OR($F46="",IFERROR(INDEX($F$5:$F$13,MATCH($F46,$E$5:$E$13,0)),"Y")="Y")),"Y","N") -> Y | L46: =IF($K46="N",0,IF(IF($C$6="Auction",$H46,$I46)=0,0,ROUNDUP(IF($C$6="Auction",$H46,$I46)*(1+IF($J46="Y",$C$10,0)),0))) -> 5 | M46: C3FS; C4FS | N46: 0 | O46: =MAX(WORKDAY($P$42,1+$N46,Holidays!$B$5:$B$60),WORKDAY($P$43,1+$N46,Holidays!$B$5:$B$60)) -> 46499 | P46: =IF($K46="N",WORKDAY($O46,-1,Holidays!$B$5:$B$60),IF($L46=0,$O46,WORKDAY($O46,$L46-1,Holidays!$B$5:$B$60))) -> 46505 | Q46: Not started | R46: =IF(AND($G46="HOLD",$K46="Y"),"■ HOLD: go/no-go. ","")
A47: D2 | B47: D First fix | C47: Plumbing and heating first fix | D47: Plumber | E47: Both | F47: Heating/boiler | H47: 4 | I47: 4 | J47: Y | K47: =IF(AND(OR($E47="Both",$E47=$C$6),OR($F47="",IFERROR(INDEX($F$5:$F$13,MATCH($F47,$E$5:$E$13,0)),"Y")="Y")),"Y","N") -> Y | L47: =IF($K47="N",0,IF(IF($C$6="Auction",$H47,$I47)=0,0,ROUNDUP(IF($C$6="Auction",$H47,$I47)*(1+IF($J47="Y",$C$10,0)),0))) -> 5 | M47: C3FS; C4FS | N47: 1 | O47: =MAX(WORKDAY($P$42,1+$N47,Holidays!$B$5:$B$60),WORKDAY($P$43,1+$N47,Holidays!$B$5:$B$60)) -> 46500 | P47: =IF($K47="N",WORKDAY($O47,-1,Holidays!$B$5:$B$60),IF($L47=0,$O47,WORKDAY($O47,$L47-1,Holidays!$B$5:$B$60))) -> 46506 | Q47: Not started | R47: =IF(AND($G47="HOLD",$K47="Y"),"■ HOLD: go/no-go. ","") | S47: Starts 1 day after electrics to share the site.
A48: D3 | B48: D First fix | C48: Joinery first fix (stud walls, linings) | D48: Carpenter | E48: Both | H48: 3 | I48: 3 | J48: Y | K48: =IF(AND(OR($E48="Both",$E48=$C$6),OR($F48="",IFERROR(INDEX($F$5:$F$13,MATCH($F48,$E$5:$E$13,0)),"Y")="Y")),"Y","N") -> Y | L48: =IF($K48="N",0,IF(IF($C$6="Auction",$H48,$I48)=0,0,ROUNDUP(IF($C$6="Auction",$H48,$I48)*(1+IF($J48="Y",$C$10,0)),0))) -> 4 | M48: C3FS; C4FS | N48: 0 | O48: =MAX(WORKDAY($P$42,1+$N48,Holidays!$B$5:$B$60),WORKDAY($P$43,1+$N48,Holidays!$B$5:$B$60)) -> 46499 | P48: =IF($K48="N",WORKDAY($O48,-1,Holidays!$B$5:$B$60),IF($L48=0,$O48,WORKDAY($O48,$L48-1,Holidays!$B$5:$B$60))) -> 46504 | Q48: Not started | R48: =IF(AND($G48="HOLD",$K48="Y"),"■ HOLD: go/no-go. ","")
A49: D4 | B49: D First fix | C49: First-fix check before boarding (electrician / Building Control if notifiable) | D49: Builder | E49: Both | G49: HOLD | H49: 1 | I49: 1 | J49: N | K49: =IF(AND(OR($E49="Both",$E49=$C$6),OR($F49="",IFERROR(INDEX($F$5:$F$13,MATCH($F49,$E$5:$E$13,0)),"Y")="Y")),"Y","N") -> Y | L49: =IF($K49="N",0,IF(IF($C$6="Auction",$H49,$I49)=0,0,ROUNDUP(IF($C$6="Auction",$H49,$I49)*(1+IF($J49="Y",$C$10,0)),0))) -> 1 | M49: D1FS; D2FS; D3FS | N49: 0 | O49: =MAX(WORKDAY($P$46,1+$N49,Holidays!$B$5:$B$60),WORKDAY($P$47,1+$N49,Holidays!$B$5:$B$60),WORKDAY($P$48,1+$N49,Holidays!$B$5:$B$60)) -> 46507 | P49: =IF($K49="N",WORKDAY($O49,-1,Holidays!$B$5:$B$60),IF($L49=0,$O49,WORKDAY($O49,$L49-1,Holidays!$B$5:$B$60))) -> 46507 | Q49: Not started | R49: =IF(AND($G49="HOLD",$K49="Y"),"■ HOLD: go/no-go. ","") -> ■ HOLD: go/no-go. | S49: Photograph every wall before boarding.
A50: E1 | B50: E Plaster | C50: Board, plaster and skim | D50: Plasterer | E50: Both | H50: 6 | I50: 6 | J50: Y | K50: =IF(AND(OR($E50="Both",$E50=$C$6),OR($F50="",IFERROR(INDEX($F$5:$F$13,MATCH($F50,$E$5:$E$13,0)),"Y")="Y")),"Y","N") -> Y | L50: =IF($K50="N",0,IF(IF($C$6="Auction",$H50,$I50)=0,0,ROUNDUP(IF($C$6="Auction",$H50,$I50)*(1+IF($J50="Y",$C$10,0)),0))) -> 7 | M50: D4FS; C5FS; C6FS | N50: 0 | O50: =MAX(WORKDAY($P$49,1+$N50,Holidays!$B$5:$B$60),WORKDAY($P$44,1+$N50,Holidays!$B$5:$B$60),WORKDAY($P$45,1+$N50,Holidays!$B$5:$B$60)) -> 46511 | P50: =IF($K50="N",WORKDAY($O50,-1,Holidays!$B$5:$B$60),IF($L50=0,$O50,WORKDAY($O50,$L50-1,Holidays!$B$5:$B$60))) -> 46519 | Q50: Not started | R50: =IF(AND($G50="HOLD",$K50="Y"),"■ HOLD: go/no-go. ","") | S50: Roof watertight and windows in first.
A51: E2 | B51: E Plaster | C51: Drying out (winter allowance added automatically Nov–Feb) | D51: — | E51: Both | H51: 5 | I51: 5 | J51: N | K51: =IF(AND(OR($E51="Both",$E51=$C$6),OR($F51="",IFERROR(INDEX($F$5:$F$13,MATCH($F51,$E$5:$E$13,0)),"Y")="Y")),"Y","N") -> Y | L51: =IF($K51="N",0,IF(IF($C$6="Auction",$H51,$I51)=0,0,ROUNDUP(IF($C$6="Auction",$H51,$I51)*(1+IF($J51="Y",$C$10,0)),0)+IF(OR(MONTH($O51)>=11,MONTH($O51)<=2),$C$11,0))) -> 5 | M51: E1FS | N51: 0 | O51: =WORKDAY($P$50,1+$N51,Holidays!$B$5:$B$60) -> 46520 | P51: =IF($K51="N",WORKDAY($O51,-1,Holidays!$B$5:$B$60),IF($L51=0,$O51,WORKDAY($O51,$L51-1,Holidays!$B$5:$B$60))) -> 46526 | Q51: Not started | R51: =IF(AND($G51="HOLD",$K51="Y"),"■ HOLD: go/no-go. ","")&IF(OR(MONTH($O51)>=11,MONTH($O51)<=2),"Winter drying allowance added. ","") | S51: Heat + dehumidifiers. Painting too early = cracking and bloom.
A52: E3 | B52: E Plaster | C52: Mist coat | D52: Decorator | E52: Both | H52: 2 | I52: 2 | J52: Y | K52: =IF(AND(OR($E52="Both",$E52=$C$6),OR($F52="",IFERROR(INDEX($F$5:$F$13,MATCH($F52,$E$5:$E$13,0)),"Y")="Y")),"Y","N") -> Y | L52: =IF($K52="N",0,IF(IF($C$6="Auction",$H52,$I52)=0,0,ROUNDUP(IF($C$6="Auction",$H52,$I52)*(1+IF($J52="Y",$C$10,0)),0))) -> 3 | M52: E2FS | N52: 0 | O52: =WORKDAY($P$51,1+$N52,Holidays!$B$5:$B$60) -> 46527 | P52: =IF($K52="N",WORKDAY($O52,-1,Holidays!$B$5:$B$60),IF($L52=0,$O52,WORKDAY($O52,$L52-1,Holidays!$B$5:$B$60))) -> 46531 | Q52: Not started | R52: =IF(AND($G52="HOLD",$K52="Y"),"■ HOLD: go/no-go. ","")
A53: F1 | B53: F Second fix & finish | C53: Kitchen fit | D53: Kitchen fitter | E53: Both | F53: Kitchen | H53: 4 | I53: 4 | J53: Y | K53: =IF(AND(OR($E53="Both",$E53=$C$6),OR($F53="",IFERROR(INDEX($F$5:$F$13,MATCH($F53,$E$5:$E$13,0)),"Y")="Y")),"Y","N") -> Y | L53: =IF($K53="N",0,IF(IF($C$6="Auction",$H53,$I53)=0,0,ROUNDUP(IF($C$6="Auction",$H53,$I53)*(1+IF($J53="Y",$C$10,0)),0))) -> 5 | M53: E3FS; B5FS | N53: 0 | O53: =MAX(WORKDAY($P$52,1+$N53,Holidays!$B$5:$B$60),WORKDAY($P$37,1+$N53,Holidays!$B$5:$B$60)) -> 46532 | P53: =IF($K53="N",WORKDAY($O53,-1,Holidays!$B$5:$B$60),IF($L53=0,$O53,WORKDAY($O53,$L53-1,Holidays!$B$5:$B$60))) -> 46539 | Q53: Not started | R53: =IF(AND($G53="HOLD",$K53="Y"),"■ HOLD: go/no-go. ","")
A54: F2 | B54: F Second fix & finish | C54: Bathroom fit and tiling | D54: Plumber / tiler | E54: Both | F54: Bathroom | H54: 5 | I54: 5 | J54: Y | K54: =IF(AND(OR($E54="Both",$E54=$C$6),OR($F54="",IFERROR(INDEX($F$5:$F$13,MATCH($F54,$E$5:$E$13,0)),"Y")="Y")),"Y","N") -> Y | L54: =IF($K54="N",0,IF(IF($C$6="Auction",$H54,$I54)=0,0,ROUNDUP(IF($C$6="Auction",$H54,$I54)*(1+IF($J54="Y",$C$10,0)),0))) -> 6 | M54: E3FS | N54: 0 | O54: =WORKDAY($P$52,1+$N54,Holidays!$B$5:$B$60) -> 46532 | P54: =IF($K54="N",WORKDAY($O54,-1,Holidays!$B$5:$B$60),IF($L54=0,$O54,WORKDAY($O54,$L54-1,Holidays!$B$5:$B$60))) -> 46540 | Q54: Not started | R54: =IF(AND($G54="HOLD",$K54="Y"),"■ HOLD: go/no-go. ","")
A55: F3 | B55: F Second fix & finish | C55: Electrical second fix and testing | D55: Electrician | E55: Both | H55: 2 | I55: 2 | J55: Y | K55: =IF(AND(OR($E55="Both",$E55=$C$6),OR($F55="",IFERROR(INDEX($F$5:$F$13,MATCH($F55,$E$5:$E$13,0)),"Y")="Y")),"Y","N") -> Y | L55: =IF($K55="N",0,IF(IF($C$6="Auction",$H55,$I55)=0,0,ROUNDUP(IF($C$6="Auction",$H55,$I55)*(1+IF($J55="Y",$C$10,0)),0))) -> 3 | M55: F1FS; F2FS | N55: 0 | O55: =MAX(WORKDAY($P$53,1+$N55,Holidays!$B$5:$B$60),WORKDAY($P$54,1+$N55,Holidays!$B$5:$B$60)) -> 46541 | P55: =IF($K55="N",WORKDAY($O55,-1,Holidays!$B$5:$B$60),IF($L55=0,$O55,WORKDAY($O55,$L55-1,Holidays!$B$5:$B$60))) -> 46545 | Q55: Not started | R55: =IF(AND($G55="HOLD",$K55="Y"),"■ HOLD: go/no-go. ","")
A56: F4 | B56: F Second fix & finish | C56: Plumbing / heating second fix; boiler commissioned | D56: Plumber / Gas Safe | E56: Both | H56: 2 | I56: 2 | J56: Y | K56: =IF(AND(OR($E56="Both",$E56=$C$6),OR($F56="",IFERROR(INDEX($F$5:$F$13,MATCH($F56,$E$5:$E$13,0)),"Y")="Y")),"Y","N") -> Y | L56: =IF($K56="N",0,IF(IF($C$6="Auction",$H56,$I56)=0,0,ROUNDUP(IF($C$6="Auction",$H56,$I56)*(1+IF($J56="Y",$C$10,0)),0))) -> 3 | M56: F1FS; F2FS | N56: 0 | O56: =MAX(WORKDAY($P$53,1+$N56,Holidays!$B$5:$B$60),WORKDAY($P$54,1+$N56,Holidays!$B$5:$B$60)) -> 46541 | P56: =IF($K56="N",WORKDAY($O56,-1,Holidays!$B$5:$B$60),IF($L56=0,$O56,WORKDAY($O56,$L56-1,Holidays!$B$5:$B$60))) -> 46545 | Q56: Not started | R56: =IF(AND($G56="HOLD",$K56="Y"),"■ HOLD: go/no-go. ","")
A57: F5 | B57: F Second fix & finish | C57: Joinery second fix (doors, skirting, architrave) | D57: Carpenter | E57: Both | H57: 3 | I57: 3 | J57: Y | K57: =IF(AND(OR($E57="Both",$E57=$C$6),OR($F57="",IFERROR(INDEX($F$5:$F$13,MATCH($F57,$E$5:$E$13,0)),"Y")="Y")),"Y","N") -> Y | L57: =IF($K57="N",0,IF(IF($C$6="Auction",$H57,$I57)=0,0,ROUNDUP(IF($C$6="Auction",$H57,$I57)*(1+IF($J57="Y",$C$10,0)),0))) -> 4 | M57: E3FS | N57: 0 | O57: =WORKDAY($P$52,1+$N57,Holidays!$B$5:$B$60) -> 46532 | P57: =IF($K57="N",WORKDAY($O57,-1,Holidays!$B$5:$B$60),IF($L57=0,$O57,WORKDAY($O57,$L57-1,Holidays!$B$5:$B$60))) -> 46535 | Q57: Not started | R57: =IF(AND($G57="HOLD",$K57="Y"),"■ HOLD: go/no-go. ","")
A58: F6 | B58: F Second fix & finish | C58: Decoration | D58: Decorator | E58: Both | H58: 6 | I58: 6 | J58: Y | K58: =IF(AND(OR($E58="Both",$E58=$C$6),OR($F58="",IFERROR(INDEX($F$5:$F$13,MATCH($F58,$E$5:$E$13,0)),"Y")="Y")),"Y","N") -> Y | L58: =IF($K58="N",0,IF(IF($C$6="Auction",$H58,$I58)=0,0,ROUNDUP(IF($C$6="Auction",$H58,$I58)*(1+IF($J58="Y",$C$10,0)),0))) -> 7 | M58: F3FS; F4FS; F5FS | N58: 0 | O58: =MAX(WORKDAY($P$55,1+$N58,Holidays!$B$5:$B$60),WORKDAY($P$56,1+$N58,Holidays!$B$5:$B$60),WORKDAY($P$57,1+$N58,Holidays!$B$5:$B$60)) -> 46546 | P58: =IF($K58="N",WORKDAY($O58,-1,Holidays!$B$5:$B$60),IF($L58=0,$O58,WORKDAY($O58,$L58-1,Holidays!$B$5:$B$60))) -> 46554 | Q58: Not started | R58: =IF(AND($G58="HOLD",$K58="Y"),"■ HOLD: go/no-go. ","")
A59: F7 | B59: F Second fix & finish | C59: Flooring | D59: Flooring fitter | E59: Both | H59: 2 | I59: 2 | J59: Y | K59: =IF(AND(OR($E59="Both",$E59=$C$6),OR($F59="",IFERROR(INDEX($F$5:$F$13,MATCH($F59,$E$5:$E$13,0)),"Y")="Y")),"Y","N") -> Y | L59: =IF($K59="N",0,IF(IF($C$6="Auction",$H59,$I59)=0,0,ROUNDUP(IF($C$6="Auction",$H59,$I59)*(1+IF($J59="Y",$C$10,0)),0))) -> 3 | M59: F6FS | N59: 0 | O59: =WORKDAY($P$58,1+$N59,Holidays!$B$5:$B$60) -> 46555 | P59: =IF($K59="N",WORKDAY($O59,-1,Holidays!$B$5:$B$60),IF($L59=0,$O59,WORKDAY($O59,$L59-1,Holidays!$B$5:$B$60))) -> 46559 | Q59: Not started | R59: =IF(AND($G59="HOLD",$K59="Y"),"■ HOLD: go/no-go. ","")
A60: F8 | B60: F Second fix & finish | C60: Kerb appeal: front door, paint, garden tidy | D60: Builder | E60: Both | H60: 2 | I60: 2 | J60: Y | K60: =IF(AND(OR($E60="Both",$E60=$C$6),OR($F60="",IFERROR(INDEX($F$5:$F$13,MATCH($F60,$E$5:$E$13,0)),"Y")="Y")),"Y","N") -> Y | L60: =IF($K60="N",0,IF(IF($C$6="Auction",$H60,$I60)=0,0,ROUNDUP(IF($C$6="Auction",$H60,$I60)*(1+IF($J60="Y",$C$10,0)),0))) -> 3 | M60: F6FS | N60: 0 | O60: =WORKDAY($P$58,1+$N60,Holidays!$B$5:$B$60) -> 46555 | P60: =IF($K60="N",WORKDAY($O60,-1,Holidays!$B$5:$B$60),IF($L60=0,$O60,WORKDAY($O60,$L60-1,Holidays!$B$5:$B$60))) -> 46559 | Q60: Not started | R60: =IF(AND($G60="HOLD",$K60="Y"),"■ HOLD: go/no-go. ","")&IF(AND($K60="Y",OR(MONTH($O60)>=11,MONTH($O60)<=2)),"⚠ External work in Nov–Feb: weather risk. ","") | S60: Training rule: £1 of refurb should add £3 of value.
A61: G1 | B61: G Sign-off | C61: Certificates: EIC (Part P), Gas Safe / Building Regs, FENSA, Building Control completion | D61: Trades | E61: Both | H61: 3 | I61: 3 | J61: N | K61: =IF(AND(OR($E61="Both",$E61=$C$6),OR($F61="",IFERROR(INDEX($F$5:$F$13,MATCH($F61,$E$5:$E$13,0)),"Y")="Y")),"Y","N") -> Y | L61: =IF($K61="N",0,IF(IF($C$6="Auction",$H61,$I61)=0,0,ROUNDUP(IF($C$6="Auction",$H61,$I61)*(1+IF($J61="Y",$C$10,0)),0))) -> 3 | M61: F3FS; F4FS | N61: 0 | O61: =MAX(WORKDAY($P$55,1+$N61,Holidays!$B$5:$B$60),WORKDAY($P$56,1+$N61,Holidays!$B$5:$B$60)) -> 46546 | P61: =IF($K61="N",WORKDAY($O61,-1,Holidays!$B$5:$B$60),IF($L61=0,$O61,WORKDAY($O61,$L61-1,Holidays!$B$5:$B$60))) -> 46548 | Q61: Not started | R61: =IF(AND($G61="HOLD",$K61="Y"),"■ HOLD: go/no-go. ","") | S61: Buyer's solicitor will ask for every one. No certs = delayed exchange.
A62: G2 | B62: G Sign-off | C62: Snagging walk-round and fixes | D62: Paul + builder | E62: Both | H62: 3 | I62: 3 | J62: N | K62: =IF(AND(OR($E62="Both",$E62=$C$6),OR($F62="",IFERROR(INDEX($F$5:$F$13,MATCH($F62,$E$5:$E$13,0)),"Y")="Y")),"Y","N") -> Y | L62: =IF($K62="N",0,IF(IF($C$6="Auction",$H62,$I62)=0,0,ROUNDUP(IF($C$6="Auction",$H62,$I62)*(1+IF($J62="Y",$C$10,0)),0))) -> 3 | M62: F7FS; F8FS | N62: 0 | O62: =MAX(WORKDAY($P$59,1+$N62,Holidays!$B$5:$B$60),WORKDAY($P$60,1+$N62,Holidays!$B$5:$B$60)) -> 46560 | P62: =IF($K62="N",WORKDAY($O62,-1,Holidays!$B$5:$B$60),IF($L62=0,$O62,WORKDAY($O62,$L62-1,Holidays!$B$5:$B$60))) -> 46562 | Q62: Not started | R62: =IF(AND($G62="HOLD",$K62="Y"),"■ HOLD: go/no-go. ","")
A63: G3 | B63: G Sign-off | C63: PRACTICAL COMPLETION: stage payment (5% retention held) | D63: Paul | E63: Both | G63: HOLD | H63: 0 | I63: 0 | J63: N | K63: =IF(AND(OR($E63="Both",$E63=$C$6),OR($F63="",IFERROR(INDEX($F$5:$F$13,MATCH($F63,$E$5:$E$13,0)),"Y")="Y")),"Y","N") -> Y | L63: =IF($K63="N",0,IF(IF($C$6="Auction",$H63,$I63)=0,0,ROUNDUP(IF($C$6="Auction",$H63,$I63)*(1+IF($J63="Y",$C$10,0)),0))) -> 0 | M63: G2FS | N63: 0 | O63: =WORKDAY($P$62,1+$N63,Holidays!$B$5:$B$60) -> 46563 | P63: =IF($K63="N",WORKDAY($O63,-1,Holidays!$B$5:$B$60),IF($L63=0,$O63,WORKDAY($O63,$L63-1,Holidays!$B$5:$B$60))) -> 46563 | Q63: Not started | R63: =IF(AND($G63="HOLD",$K63="Y"),"■ HOLD: go/no-go. ","") -> ■ HOLD: go/no-go. | S63: Sign off only when the snag list is clear.
A64: G4 | B64: G Sign-off | C64: EPC commissioned | D64: Assessor | E64: Both | H64: 2 | I64: 2 | J64: N | K64: =IF(AND(OR($E64="Both",$E64=$C$6),OR($F64="",IFERROR(INDEX($F$5:$F$13,MATCH($F64,$E$5:$E$13,0)),"Y")="Y")),"Y","N") -> Y | L64: =IF($K64="N",0,IF(IF($C$6="Auction",$H64,$I64)=0,0,ROUNDUP(IF($C$6="Auction",$H64,$I64)*(1+IF($J64="Y",$C$10,0)),0))) -> 2 | M64: G2FS | N64: 0 | O64: =WORKDAY($P$62,1+$N64,Holidays!$B$5:$B$60) -> 46563 | P64: =IF($K64="N",WORKDAY($O64,-1,Holidays!$B$5:$B$60),IF($L64=0,$O64,WORKDAY($O64,$L64-1,Holidays!$B$5:$B$60))) -> 46566 | Q64: Not started | R64: =IF(AND($G64="HOLD",$K64="Y"),"■ HOLD: go/no-go. ","") | S64: Must be commissioned before marketing.
A65: G5 | B65: G Sign-off | C65: Deep clean, staging, photos and floorplan | D65: Paul | E65: Both | H65: 3 | I65: 3 | J65: N | K65: =IF(AND(OR($E65="Both",$E65=$C$6),OR($F65="",IFERROR(INDEX($F$5:$F$13,MATCH($F65,$E$5:$E$13,0)),"Y")="Y")),"Y","N") -> Y | L65: =IF($K65="N",0,IF(IF($C$6="Auction",$H65,$I65)=0,0,ROUNDUP(IF($C$6="Auction",$H65,$I65)*(1+IF($J65="Y",$C$10,0)),0))) -> 3 | M65: G2FS | N65: 0 | O65: =WORKDAY($P$62,1+$N65,Holidays!$B$5:$B$60) -> 46563 | P65: =IF($K65="N",WORKDAY($O65,-1,Holidays!$B$5:$B$60),IF($L65=0,$O65,WORKDAY($O65,$L65-1,Holidays!$B$5:$B$60))) -> 46567 | Q65: Not started | R65: =IF(AND($G65="HOLD",$K65="Y"),"■ HOLD: go/no-go. ","")
A66: H1 | B66: H Sale & close-out | C66: Three agent valuations; instruct agent | D66: Paul | E66: Both | H66: 3 | I66: 3 | J66: N | K66: =IF(AND(OR($E66="Both",$E66=$C$6),OR($F66="",IFERROR(INDEX($F$5:$F$13,MATCH($F66,$E$5:$E$13,0)),"Y")="Y")),"Y","N") -> Y | L66: =IF($K66="N",0,IF(IF($C$6="Auction",$H66,$I66)=0,0,ROUNDUP(IF($C$6="Auction",$H66,$I66)*(1+IF($J66="Y",$C$10,0)),0))) -> 3 | M66: G2SS | N66: 0 | O66: =WORKDAY($O$62,$N66,Holidays!$B$5:$B$60) -> 46560 | P66: =IF($K66="N",WORKDAY($O66,-1,Holidays!$B$5:$B$60),IF($L66=0,$O66,WORKDAY($O66,$L66-1,Holidays!$B$5:$B$60))) -> 46562 | Q66: Not started | R66: =IF(AND($G66="HOLD",$K66="Y"),"■ HOLD: go/no-go. ","") | S66: Book during snagging.
A67: H2 | B67: H Sale & close-out | C67: LISTED on portals | D67: Agent | E67: Both | H67: 0 | I67: 0 | J67: N | K67: =IF(AND(OR($E67="Both",$E67=$C$6),OR($F67="",IFERROR(INDEX($F$5:$F$13,MATCH($F67,$E$5:$E$13,0)),"Y")="Y")),"Y","N") -> Y | L67: =IF($K67="N",0,IF(IF($C$6="Auction",$H67,$I67)=0,0,ROUNDUP(IF($C$6="Auction",$H67,$I67)*(1+IF($J67="Y",$C$10,0)),0))) -> 0 | M67: H1FS; G4FS; G5FS | N67: 0 | O67: =MAX(WORKDAY($P$66,1+$N67,Holidays!$B$5:$B$60),WORKDAY($P$64,1+$N67,Holidays!$B$5:$B$60),WORKDAY($P$65,1+$N67,Holidays!$B$5:$B$60)) -> 46568 | P67: =IF($K67="N",WORKDAY($O67,-1,Holidays!$B$5:$B$60),IF($L67=0,$O67,WORKDAY($O67,$L67-1,Holidays!$B$5:$B$60))) -> 46568 | Q67: Not started | R67: =IF(AND($G67="HOLD",$K67="Y"),"■ HOLD: go/no-go. ","")&IF(OR(MONTH($O67)=8,MONTH($O67)=11,MONTH($O67)=12),"⚠ Listing in a slow month (Aug/Nov/Dec). ","")
A68: H3 | B68: H Sale & close-out | C68: Viewings → sale agreed | D68: Agent | E68: Both | H68: =$C$12 -> 30 | I68: =$C$12 -> 30 | J68: N | K68: =IF(AND(OR($E68="Both",$E68=$C$6),OR($F68="",IFERROR(INDEX($F$5:$F$13,MATCH($F68,$E$5:$E$13,0)),"Y")="Y")),"Y","N") -> Y | L68: =IF($K68="N",0,IF(IF($C$6="Auction",$H68,$I68)=0,0,ROUNDUP(IF($C$6="Auction",$H68,$I68)*(1+IF($J68="Y",$C$10,0)),0))) -> 30 | M68: H2FS | N68: 0 | O68: =WORKDAY($P$67,1+$N68,Holidays!$B$5:$B$60) -> 46569 | P68: =IF($K68="N",WORKDAY($O68,-1,Holidays!$B$5:$B$60),IF($L68=0,$O68,WORKDAY($O68,$L68-1,Holidays!$B$5:$B$60))) -> 46610 | Q68: Not started | R68: =IF(AND($G68="HOLD",$K68="Y"),"■ HOLD: go/no-go. ","") | S68: Duration set in C12.
A69: H4 | B69: H Sale & close-out | C69: Memorandum of sale; buyer's mortgage valuation | D69: Agent / buyer | E69: Both | H69: 10 | I69: 10 | J69: N | K69: =IF(AND(OR($E69="Both",$E69=$C$6),OR($F69="",IFERROR(INDEX($F$5:$F$13,MATCH($F69,$E$5:$E$13,0)),"Y")="Y")),"Y","N") -> Y | L69: =IF($K69="N",0,IF(IF($C$6="Auction",$H69,$I69)=0,0,ROUNDUP(IF($C$6="Auction",$H69,$I69)*(1+IF($J69="Y",$C$10,0)),0))) -> 10 | M69: H3FS | N69: 0 | O69: =WORKDAY($P$68,1+$N69,Holidays!$B$5:$B$60) -> 46611 | P69: =IF($K69="N",WORKDAY($O69,-1,Holidays!$B$5:$B$60),IF($L69=0,$O69,WORKDAY($O69,$L69-1,Holidays!$B$5:$B$60))) -> 46624 | Q69: Not started | R69: =IF(AND($G69="HOLD",$K69="Y"),"■ HOLD: go/no-go. ","")
A70: H5 | B70: H Sale & close-out | C70: Buyer's searches, enquiries and survey; supply certificates | D70: Solicitors | E70: Both | H70: 40 | I70: 40 | J70: N | K70: =IF(AND(OR($E70="Both",$E70=$C$6),OR($F70="",IFERROR(INDEX($F$5:$F$13,MATCH($F70,$E$5:$E$13,0)),"Y")="Y")),"Y","N") -> Y | L70: =IF($K70="N",0,IF(IF($C$6="Auction",$H70,$I70)=0,0,ROUNDUP(IF($C$6="Auction",$H70,$I70)*(1+IF($J70="Y",$C$10,0)),0))) -> 40 | M70: H3FS | N70: 0 | O70: =WORKDAY($P$68,1+$N70,Holidays!$B$5:$B$60) -> 46611 | P70: =IF($K70="N",WORKDAY($O70,-1,Holidays!$B$5:$B$60),IF($L70=0,$O70,WORKDAY($O70,$L70-1,Holidays!$B$5:$B$60))) -> 46667 | Q70: Not started | R70: =IF(AND($G70="HOLD",$K70="Y"),"■ HOLD: go/no-go. ","") | S70: Chase weekly. Typical sale-agreed → completion: 12–16 weeks.
A71: H6 | B71: H Sale & close-out | C71: Exchange contracts on sale | D71: Solicitors | E71: Both | H71: 0 | I71: 0 | J71: N | K71: =IF(AND(OR($E71="Both",$E71=$C$6),OR($F71="",IFERROR(INDEX($F$5:$F$13,MATCH($F71,$E$5:$E$13,0)),"Y")="Y")),"Y","N") -> Y | L71: =IF($K71="N",0,IF(IF($C$6="Auction",$H71,$I71)=0,0,ROUNDUP(IF($C$6="Auction",$H71,$I71)*(1+IF($J71="Y",$C$10,0)),0))) -> 0 | M71: H4FS; H5FS; G1FS | N71: 0 | O71: =MAX(WORKDAY($P$69,1+$N71,Holidays!$B$5:$B$60),WORKDAY($P$70,1+$N71,Holidays!$B$5:$B$60),WORKDAY($P$61,1+$N71,Holidays!$B$5:$B$60)) -> 46668 | P71: =IF($K71="N",WORKDAY($O71,-1,Holidays!$B$5:$B$60),IF($L71=0,$O71,WORKDAY($O71,$L71-1,Holidays!$B$5:$B$60))) -> 46668 | Q71: Not started | R71: =IF(AND($G71="HOLD",$K71="Y"),"■ HOLD: go/no-go. ","")
A72: H7 | B72: H Sale & close-out | C72: SALE COMPLETION: bridge redeemed | D72: Solicitor | E72: Both | H72: 0 | I72: 0 | J72: N | K72: =IF(AND(OR($E72="Both",$E72=$C$6),OR($F72="",IFERROR(INDEX($F$5:$F$13,MATCH($F72,$E$5:$E$13,0)),"Y")="Y")),"Y","N") -> Y | L72: =IF($K72="N",0,IF(IF($C$6="Auction",$H72,$I72)=0,0,ROUNDUP(IF($C$6="Auction",$H72,$I72)*(1+IF($J72="Y",$C$10,0)),0))) -> 0 | M72: H6FS | N72: =$C$15-1 -> 9 | O72: =WORKDAY($P$71,1+$N72,Holidays!$B$5:$B$60) -> 46682 | P72: =IF($K72="N",WORKDAY($O72,-1,Holidays!$B$5:$B$60),IF($L72=0,$O72,WORKDAY($O72,$L72-1,Holidays!$B$5:$B$60))) -> 46682 | Q72: Not started | R72: =IF(AND($G72="HOLD",$K72="Y"),"■ HOLD: go/no-go. ","")&IF(($P72-$P$32)/30.44>$C$13,"⚠ Sale completes after bridge term: extension cost. ","") | S72: Lag = C15 − 1 so completion lands C15 working days after exchange.
A73: H8 | B73: H Sale & close-out | C73: Retention released (end of defects period) | D73: Paul | E73: Both | H73: 0 | I73: 0 | J73: N | K73: =IF(AND(OR($E73="Both",$E73=$C$6),OR($F73="",IFERROR(INDEX($F$5:$F$13,MATCH($F73,$E$5:$E$13,0)),"Y")="Y")),"Y","N") -> Y | L73: =IF($K73="N",0,IF(IF($C$6="Auction",$H73,$I73)=0,0,ROUNDUP(IF($C$6="Auction",$H73,$I73)*(1+IF($J73="Y",$C$10,0)),0))) -> 0 | M73: G3FS | N73: 60 | O73: =WORKDAY($P$63,1+$N73,Holidays!$B$5:$B$60) -> 46651 | P73: =IF($K73="N",WORKDAY($O73,-1,Holidays!$B$5:$B$60),IF($L73=0,$O73,WORKDAY($O73,$L73-1,Holidays!$B$5:$B$60))) -> 46651 | Q73: Not started | R73: =IF(AND($G73="HOLD",$K73="Y"),"■ HOLD: go/no-go. ","") | S73: Lag 60 WD ≈ 3 months after practical completion.
A74: H9 | B74: H Sale & close-out | C74: Close-out: final P&L vs appraisal in DealsDash; lessons learned | D74: Paul | E74: Both | H74: 2 | I74: 2 | J74: N | K74: =IF(AND(OR($E74="Both",$E74=$C$6),OR($F74="",IFERROR(INDEX($F$5:$F$13,MATCH($F74,$E$5:$E$13,0)),"Y")="Y")),"Y","N") -> Y | L74: =IF($K74="N",0,IF(IF($C$6="Auction",$H74,$I74)=0,0,ROUNDUP(IF($C$6="Auction",$H74,$I74)*(1+IF($J74="Y",$C$10,0)),0))) -> 2 | M74: H7FS | N74: 0 | O74: =WORKDAY($P$72,1+$N74,Holidays!$B$5:$B$60) -> 46685 | P74: =IF($K74="N",WORKDAY($O74,-1,Holidays!$B$5:$B$60),IF($L74=0,$O74,WORKDAY($O74,$L74-1,Holidays!$B$5:$B$60))) -> 46686 | Q74: Not started | R74: =IF(AND($G74="HOLD",$K74="Y"),"■ HOLD: go/no-go. ","") | S74: Feed actual durations back into this template.

Sheet Holidays
A1: Non-working days used by every date formula
A2: England & Wales bank holidays computed for 2026–2028 — verify at gov.uk/bank-holidays. Trade shutdown days are editable; add your own (e.g. crew holidays) in the yellow rows.
A4: Description | B4: Date
A5: Christmas / Boxing Day (substitute if weekend) | B5: 46381
A6: Christmas / Boxing Day (substitute if weekend) | B6: 46384
A7: Trade Christmas shutdown (editable) | B7: 46385
A8: Trade Christmas shutdown (editable) | B8: 46386
A9: Trade Christmas shutdown (editable) | B9: 46387
A10: New Year's Day | B10: 46388
A11: Good Friday | B11: 46472
A12: Easter Monday | B12: 46475
A13: Early May bank holiday | B13: 46510
A14: Spring bank holiday | B14: 46538
A15: Summer bank holiday | B15: 46629
A16: Christmas / Boxing Day (substitute if weekend) | B16: 46748
... A28: Christmas / Boxing Day (substitute if weekend) | B28: 47113
